{
    "2389": "\u0120conf",
    "1694": "\u0120being",
    "74": "k",
    "2579": "\u0120red",
    "1032": "13",
    "3513": "Be",
    "1172": "\u0120fe",
    "1664": "\u0120well",
    "1548": "He",
    "1825": "\u0120open",
    "2083": "_H",
    "827": "####",
    "4": "%",
    "3901": ".spring",
    "3727": "\u0120makes",
    "2434": "TR",
    "3462": "pare",
    "3134": "================================",
    "2220": "opyright",
    "678": "Name",
    "1958": "34",
    "1156": "\u0120sc",
    "3520": "ney",
    "3012": "ention",
    "1047": "\u0120had",
    "3030": "avig",
    "329": "ad",
    "1666": "\u0120As",
    "1266": "../",
    "2128": "\u0120team",
    "1178": "word",
    "1424": "\u0120spec",
    "42": "K",
    "216": "\u011c",
    "3092": "\u0120My",
    "52": "U",
    "798": "key",
    "3389": "\u0120late",
    "2175": "\u0120Get",
    "4078": "\u0120Type",
    "2516": "++)",
    "696": ")\u010a\u010a",
    "1409": "ough",
    "2219": "\u0120dep",
    "3856": "\u0120pract",
    "3001": "!!",
    "544": "ff",
    "370": "ab",
    "70": "g",
    "4074": "\u0120admin",
    "3607": "Method",
    "2309": "default",
    "1141": "amp",
    "117": "\u00b9",
    "125": "\u00c1",
    "1103": "url",
    "4084": "cket",
    "2024": "\u0120ter",
    "1507": "ED",
    "919": "ions",
    "1692": "Man",
    "3605": "\u0120\"/",
    "61": "^",
    "2418": "\u0120Man",
    "94": "\u00a1",
    "921": "\u0120Ch",
    "2621": "uccess",
    "470": "\u0120com",
    "2459": "_ST",
    "398": "ly",
    "1243": "\u0120then",
    "1033": "ervice",
    "2555": "\u0120something",
    "1249": "heck",
    "3106": "Entity",
    "3976": "Per",
    "3633": "ony",
    "4005": ".</",
    "2849": "\u0120cell",
    "3674": "\u0120social",
    "3877": ".view",
    "3593": "node",
    "3648": "New",
    "1315": "right",
    "2643": "\u0120might",
    "2482": "ules",
    "1164": "\u0109\u0109\u0109\u0109\u0109",
    "31": "@",
    "3717": "\u0120connection",
    "1779": "select",
    "3858": "ctx",
    "2284": ">(",
    "2491": "49",
    "2335": "ential",
    "928": "string",
    "353": "\u0120*",
    "3037": "pecial",
    "1575": "sole",
    "2833": "plement",
    "505": "\u0120from",
    "1027": "\u0120been",
    "4018": "\u0120cut",
    "964": "IT",
    "2649": "ada",
    "3176": "pository",
    "502": "\u0120new",
    "2924": "idden",
    "2945": "options",
    "286": "\u0120\u0120\u0120\u0120\u0120\u0120\u0120",
    "2154": "irt",
    "3382": "\";\u010a\u010a",
    "675": "aw",
    "3889": "__(",
    "610": "\u0120str",
    "1771": "ains",
    "1434": "--------------------------------",
    "3036": "ilt",
    "3834": "\u0120interface",
    "2197": "\u0120beg",
    "2942": "\u0120organ",
    "1314": "\u0120right",
    "2653": "\u0120hard",
    "3277": "\u0120When",
    "3209": "\u00c3\u00a7",
    "3841": "je",
    "195": "\u0107",
    "1875": "\"\u010a\u010a",
    "2986": ".println",
    "26": ";",
    "1453": "Im",
    "482": "\u0120-",
    "3704": "_SE",
    "3894": "[j",
    "1566": "\u0120last",
    "1080": "\u0120co",
    "2544": "ither",
    "3270": "\u0120\"\"\"\u010a",
    "1887": "\u0120system",
    "3706": "(w",
    "2789": "\u0109case",
    "4007": "\u0120study",
    "3357": "inate",
    "3126": "Handler",
    "155": "\u00df",
    "782": "pro",
    "2863": "\u0120stat",
    "1717": "\u0120\u00c3",
    "3138": "_get",
    "2319": "oh",
    "1142": "ied",
    "260": "\u0120\u0120\u0120\u0120\u0120\u0120\u0120\u0120",
    "2795": "\u0120says",
    "2449": "\u0120element",
    "3656": ".Collections",
    "3198": "Vis",
    "1573": "ollow",
    "1583": "\u0120/**\u010a",
    "1223": "ower",
    "2597": "\u0120await",
    "3444": "ana",
    "1074": "line",
    "705": "),",
    "2208": "button",
    "3709": "\u0120inc",
    "3120": "\u0120\\\u010a",
    "274": "\u0120s",
    "3691": "\u0120food",
    "775": "\u0120else",
    "1782": "\u0120differ",
    "3985": "////////////////////////////////",
    "490": "\u0120tr",
    "903": "****************",
    "1410": "orld",
    "1502": "User",
    "2063": "come",
    "2442": "-t",
    "1209": "((",
    "2876": "\u0120Not",
    "3505": "\\\\",
    "688": "vent",
    "563": "tring",
    "341": "\u0120{\u010a",
    "1855": "\u0120each",
    "1757": "package",
    "894": "ry",
    "1494": "ah",
    "2519": "Line",
    "988": "ates",
    "2794": "\u0120OR",
    "427": "ht",
    "1388": ".add",
    "334": "**",
    "1031": "nc",
    "965": "EN",
    "2673": "\u0120height",
    "2903": "Number",
    "306": "ent",
    "2479": "\u0120len",
    "2206": "\u0120Me",
    "351": "ag",
    "3306": "sl",
    "4030": "region",
    "1833": "\u0120follow",
    "862": "\u0109return",
    "2593": "\u0120eas",
    "1953": "IG",
    "600": "unction",
    "604": "pp",
    "2198": "CH",
    "3765": "\u0120Ab",
    "723": "add",
    "3172": "mb",
    "2163": "\u0120left",
    "2291": "\u0120fore",
    "3931": "IST",
    "250": "\u013e",
    "2273": "\u0120float",
    "3927": "\u0120individual",
    "3487": "56",
    "1700": "{\u010d\u010a",
    "2530": "ours",
    "3788": "\u0120https",
    "3189": "\u0120wr",
    "543": "all",
    "1407": "result",
    "1999": "Class",
    "1306": "\u0120after",
    "1729": "by",
    "257": "\u0120\u0120\u0120\u0120",
    "251": "\u013f",
    "231": "\u012b",
    "1743": "summary",
    "2342": "\u0120\u0120\u0120\u0120\u0120\u0120\u0120\u0120\u0120\u0120\u0120\u0120\u0120\u0120",
    "2152": "CE",
    "2112": ".N",
    "814": "\u0120they",
    "635": "ite",
    "3239": "env",
    "2713": "\u0120update",
    "694": "\u0120</",
    "1234": "\u0120under",
    "312": "\u0120re",
    "2840": "\u0120gl",
    "992": "inal",
    "3587": ".J",
    "2258": "lected",
    "1162": "\u0120case",
    "36": "E",
    "747": "li",
    "2865": "\u0120load",
    "2242": "\u0120config",
    "1392": "ments",
    "2806": "\u0120View",
    "3267": "isk",
    "2062": "_list",
    "1955": "eta",
    "315": "\u0120of",
    "3553": "eneric",
    "46": "O",
    "2782": "Ed",
    "3999": "\u0120ey",
    "2611": "\u0120\u0120\u0120\u0120\u0120\u0120\u0120\u0120\u0120\u0120\u0120\u0120\u0120\u0120\u0120\u0120\u0120\u0120\u0120\u0120\u0120",
    "1506": "\u00d0\u00b0",
    "909": "\")",
    "876": "gh",
    "2721": "95",
    "1203": "\u0120back",
    "2035": "\u0120place",
    "2241": "_RE",
    "2080": "\u0120struct",
    "1193": "\u0120only",
    "3398": "_user",
    "2364": "abled",
    "3298": "\u0120Act",
    "2008": "sub",
    "586": "\u0120public",
    "509": "ld",
    "2238": "Component",
    "2468": "\u0120At",
    "2227": "arm",
    "1843": "image",
    "2091": "option",
    "2787": "ById",
    "1125": "));\u010a",
    "593": "que",
    "1503": "ased",
    "111": "\u00b3",
    "1052": "\u0120file",
    "1792": "(new",
    "1628": "\u0120And",
    "998": "to",
    "2623": "\u0120\u0120\u0120\u0120\u0120\u0120\u0120\u0120\u0120\u0120\u0120\u0120\u0120\u0120\u0120\u0120\u0120\u0120\u0120\u0120\u0120\u0120\u0120\u0120\u0120\u0120\u0120\u0120\u0120\u0120\u0120\u0120\u0120\u0120\u0120\u0120\u0120\u0120\u0120",
    "369": "\u0120for",
    "1270": "'\u010a",
    "3409": "now",
    "255": "\u0143",
    "3264": "98",
    "1732": "\u0120person",
    "3026": "\u0120men",
    "2125": "link",
    "19": "4",
    "2853": "\u0120cost",
    "1822": "><",
    "3162": "structor",
    "3273": "\u0120po",
    "1719": "\u0120param",
    "3471": "umer",
    "193": "\u0105",
    "3249": "\u0120why",
    "2407": "cur",
    "129": "\u00c5",
    "2363": "\u0120book",
    "2477": "\u0120pop",
    "355": "us",
    "2548": "resh",
    "1808": "\u0120NULL",
    "2793": "\u0120invest",
    "58": "[",
    "1058": "class",
    "3101": "300",
    "2987": "ulation",
    "3590": "DB",
    "218": "\u011e",
    "3684": "next",
    "248": "\u013c",
    "375": "pe",
    "1885": "off",
    "247": "\u013b",
    "172": "\u00f0",
    "3775": "\u0120fail",
    "1881": "\u0120\u0120\u0120\u0120\u0120\u0120\u0120\u0120\u0120\u0120",
    "198": "\u010a",
    "2302": "xt",
    "811": "ations",
    "1110": "Com",
    "1800": "mit",
    "3883": "Options",
    "960": ".b",
    "3386": "Inter",
    "1331": "mp",
    "4027": "\u0120fire",
    "3643": "swer",
    "2532": "\u0120service",
    "1147": "als",
    "1603": "\u0120before",
    "1354": "ins",
    "1599": "ected",
    "653": "\u0120un",
    "1019": "void",
    "266": "at",
    "176": "\u00f4",
    "503": "\u0120j",
    "501": "pl",
    "3687": "\u0120indiv",
    "2380": "\u0120three",
    "2870": "upport",
    "3777": "\u0120component",
    "3737": "typ",
    "3953": "\u0120games",
    "3071": "adding",
    "2929": "Query",
    "2601": "odes",
    "1377": "\u0120dr",
    "3286": "\u0120btn",
    "1890": "\u0120same",
    "3906": "mm",
    "2078": "US",
    "2039": "private",
    "3731": "\u0120abs",
    "2723": "\u0120link",
    "2262": "\u0120content",
    "6": "'",
    "3178": "uk",
    "234": "\u012e",
    "3519": "amera",
    "59": "\\",
    "697": "Re",
    "1724": "********************************",
    "1332": "\u0120min",
    "1504": "\u0120{\u010a\u010a",
    "3852": "any",
    "2272": ".ex",
    "51": "T",
    "2572": "uilder",
    "308": "\u0120n",
    "764": "ph",
    "143": "\u00d3",
    "4067": "________",
    "3869": "\u0120\u00c3\u0142",
    "1909": ",\u010d\u010a",
    "3512": "\u0120div",
    "1227": "64",
    "558": ".p",
    "776": "----------------",
    "3888": "Init",
    "1613": "},\u010a",
    "2462": "\u0109var",
    "185": "\u00fd",
    "739": ".t",
    "2190": "size",
    "3318": "\u0120working",
    "2053": "els",
    "3307": "attern",
    "3756": "\u0120device",
    "1170": "DE",
    "624": "\u0120==",
    "2928": "\u0120\u00e2",
    "1092": "loc",
    "3079": "itional",
    "430": "\u0120that",
    "2016": "\u0120mov",
    "2533": "\u0120since",
    "2966": "_str",
    "3796": "mail",
    "3736": "Child",
    "2201": "no",
    "2304": "05",
    "2228": "=>",
    "469": "\u0120E",
    "3527": "ipe",
    "2182": "oute",
    "2006": "\u0120IN",
    "368": "()",
    "152": "\u00dc",
    "3661": "dated",
    "3742": "iles",
    "1886": "\u0120err",
    "3338": "\u0120dat",
    "3595": "pond",
    "3436": "\u0120''",
    "1381": "########",
    "3119": "\u0120NS",
    "3554": "/b",
    "568": "\u0120he",
    "3982": "_back",
    "2028": "This",
    "233": "\u012d",
    "3459": "\u0120Form",
    "1614": "\u0120state",
    "1226": "\u0120We",
    "1402": "ember",
    "2166": "48",
    "1625": "pty",
    "591": "\u0120=>",
    "1633": "\u0120very",
    "2248": "tribute",
    "774": "eth",
    "1385": "ities",
    "1621": "\u0120\"\"",
    "84": "u",
    "2410": "\u0120power",
    "3465": "\u0120task",
    "2099": "ever",
    "2141": "ailable",
    "62": "_",
    "667": "\u0120\u0120\u0120\u0120\u0120\u0120\u0120\u0120\u0120\u0120\u0120\u0120\u0120\u0120\u0120\u0120\u0120\u0120\u0120\u0120\u0120\u0120\u0120",
    "1493": "\u0120error",
    "4037": "\u0120token",
    "935": "\u0120String",
    "1671": "Wh",
    "2464": "chem",
    "1974": "land",
    "1858": "Path",
    "1991": "Get",
    "3726": "images",
    "2981": ".label",
    "513": "\u0120se",
    "3908": "ursor",
    "3085": "\u0120offer",
    "987": "\u0120{\u010d\u010a",
    "3466": "ocus",
    "3813": "\u0120location",
    "2395": "\u0120spe",
    "3333": "eral",
    "3715": "ugin",
    "926": "ID",
    "2867": "\u0120clear",
    "118": "\u00ba",
    "224": "\u0124",
    "1214": "(self",
    "754": "bo",
    "1604": "ale",
    "2678": "\u0120small",
    "2985": "opt",
    "106": "\u00ae",
    "3365": "\u0120Eng",
    "3366": "ixed",
    "3220": "_value",
    "35": "D",
    "1827": "\u0120\u0120\u0120\u0120\u0120\u0120\u0120\u0120\u010a",
    "3428": "\u0120low",
    "3353": "Control",
    "394": "\u0120\u0120\u0120\u0120\u0120\u0120\u0120\u0120\u0120\u0120\u0120\u0120\u0120\u0120\u0120",
    "1954": "90",
    "1752": "less",
    "3329": "aring",
    "1964": "her",
    "3849": "*)",
    "609": "name",
    "1658": "fr",
    "3067": "\u0120da",
    "783": "ton",
    "1535": "(),",
    "412": "out",
    "69": "f",
    "1569": "\u00ef\u00bc",
    "1084": "\u0120\u0120\u0120\u0120\u010a",
    "4045": ".Control",
    "3240": "\u0120begin",
    "939": "sh",
    "2460": "All",
    "2819": "\u0120values",
    "3724": "Height",
    "1876": "Form",
    "2357": "\u00c3\u00a4",
    "211": "\u0117",
    "3772": "\u0120media",
    "1024": "\u0120&&",
    "2814": "\u0120mult",
    "3779": "\u0120added",
    "2129": "\u0109int",
    "2320": "-p",
    "2118": "\u00e2\u0122\u013e",
    "3966": "\u0120needs",
    "1990": "\u0120between",
    "3502": "-in",
    "810": "\u0120more",
    "2191": "ism",
    "2959": "root",
    "318": "im",
    "3373": "\u0120select",
    "3802": "\u0120claim",
    "2261": "Add",
    "1279": "ector",
    "1447": "\u0120+=",
    "1884": "\u0120those",
    "2603": "ply",
    "803": "\");\u010a",
    "2894": ".value",
    "2992": "actory",
    "3929": "\u0120-->",
    "2025": "head",
    "114": "\u00b6",
    "598": "ans",
    "53": "V",
    "3555": "(!",
    "3219": "\u0120render",
    "2437": "02",
    "1944": "oot",
    "3394": "ino",
    "674": "\u0120#",
    "912": "\u0120no",
    "4024": "\u0120went",
    "3873": "FO",
    "560": "ice",
    "3129": "translation",
    "2926": "\u0120initial",
    "3256": "arning",
    "188": "\u0100",
    "1646": "\u0120model",
    "2417": "\u0120Im",
    "790": "ST",
    "1153": "\u0120pos",
    "997": "):\u010a",
    "3068": "etch",
    "592": "ust",
    "1567": "\u0120event",
    "3657": "$this",
    "3531": "agement",
    "304": "\u0120in",
    "2059": "Sh",
    "1384": "\u0120aw",
    "1892": "uss",
    "4019": "():\u010a",
    "1586": "_D",
    "1471": "(n",
    "2656": "used",
    "895": "========",
    "156": "\u00e0",
    "2212": "\u0120around",
    "2116": "iven",
    "3040": ".Name",
    "2788": "bed",
    "975": "14",
    "979": "reate",
    "963": "urrent",
    "1430": "eter",
    "2009": "\u0120Le",
    "3696": "dr",
    "1971": "OL",
    "126": "\u00c2",
    "3423": "rt",
    "3372": "avor",
    "2474": "cope",
    "3055": "do",
    "737": "\u0120im",
    "1317": "\u0120long",
    "2162": "\u0120home",
    "3083": "\u0120OF",
    "3884": "uggest",
    "1926": "ideo",
    "1104": "ific",
    "745": "cri",
    "4009": "\u0120network",
    "2594": ".out",
    "2428": "ique",
    "2069": "(e",
    "3876": "ising",
    "1839": "\u0120href",
    "2685": "Def",
    "3745": "values",
    "1401": "\u0120key",
    "3815": "\u0120doing",
    "440": "ect",
    "271": "\u010a\u010a",
    "3532": "lev",
    "2809": "(const",
    "3504": "\u0120cover",
    "2734": "enn",
    "4013": "NU",
    "1952": "\u0120On",
    "1780": "ainer",
    "3303": "\u0109p",
    "2202": "core",
    "2702": "pring",
    "1259": "ream",
    "1057": "\u0120our",
    "1276": ".n",
    "2260": "atabase",
    "399": "urn",
    "1835": "\u0120\u0120\u0120\u0120\u0120\u0120\u0120\u0120\u0120\u0120\u0120\u0120",
    "2704": "\u0120status",
    "3213": "izer",
    "45": "N",
    "3383": "\u0120Am",
    "1338": "util",
    "893": "\u0120man",
    "3422": "ides",
    "3940": "\u0120started",
    "2282": "\u0109b",
    "1574": "icense",
    "2111": "ved",
    "2514": "\u0109private",
    "3044": "\u0120condition",
    "3381": "\u0120font",
    "1136": "ush",
    "2386": "email",
    "3157": "\u0120market",
    "3921": ".write",
    "2525": "\u0109else",
    "570": ").",
    "438": "and",
    "2365": "bug",
    "3721": "\u0120ev",
    "1978": "leg",
    "4034": "\u0120visit",
    "1630": "\u0120X",
    "3295": "vector",
    "2286": "etails",
    "2847": "\u0120cert",
    "3925": "\u0120history",
    "2271": "\u0120quest",
    "2605": "\u0120prov",
    "3855": "\\u",
    "453": "\u0120al",
    "2314": "\u0120Ind",
    "546": "ont",
    "2824": "\u0120beh",
    "1760": "\u0120prot",
    "1557": "che",
    "1364": "\u0120she",
    "1791": "uc",
    "1207": "\u0120sub",
    "3492": "\u0120word",
    "2288": "\u0120too",
    "628": "\u0120pl",
    "2180": ".ph",
    "1275": "index",
    "2581": ".create",
    "1121": "\u0120result",
    "484": "ill",
    "3473": "then",
    "3564": "\u0120porn",
    "343": "ig",
    "918": "_l",
    "3983": "first",
    "2131": "55",
    "3275": "artment",
    "500": "ype",
    "1414": "ger",
    "1199": "Text",
    "3990": "find",
    "2729": "Out",
    "2229": "aterial",
    "1175": "(t",
    "2802": "\u0120interest",
    "2590": "model",
    "1486": "\u0120point",
    "3517": "player",
    "516": ".s",
    "3617": "Pr",
    "1071": "\u0120said",
    "864": "\u0120pre",
    "3978": "iet",
    "2635": "lex",
    "44": "M",
    "3098": "\u00e0\u00b8",
    "692": "\u0120\u0120\u0120\u0120\u0120\u0120\u0120\u0120\u0120",
    "3912": "ithub",
    "3821": "\u0120watch",
    "1456": "\u0120try",
    "3635": "umb",
    "2681": "anguage",
    "1051": "\u0120were",
    "1485": "trans",
    "548": "are",
    "2503": "\u0120sit",
    "729": "ens",
    "3683": "Cell",
    "2135": "_E",
    "2872": "\u0120row",
    "2426": "otal",
    "1851": "velop",
    "1744": "\u0120que",
    "626": "St",
    "736": "ivate",
    "3144": "ecute",
    "1997": "Node",
    "2087": "Manager",
    "1530": "label",
    "976": "\u0120!=",
    "1653": "vert",
    "3575": "\u0120problem",
    "3238": ".'",
    "2443": "update",
    "2086": "lobal",
    "2767": "ponents",
    "2705": "06",
    "741": ");\u010d\u010a",
    "4002": "ARR",
    "2278": "\u0120poss",
    "223": "\u0123",
    "2217": "\u0120image",
    "631": "put",
    "2195": "...\u010a\u010a",
    "2436": "ences",
    "1359": ",\"",
    "2276": "Map",
    "3439": "\u0120adv",
    "1194": "\u0120print",
    "3567": "\u0120dev",
    "2296": "cale",
    "3150": ".class",
    "590": "oid",
    "3641": "\u0120False",
    "3135": "\u0120results",
    "2764": "\u0120valid",
    "2784": "aut",
    "556": "ire",
    "289": "\u0120w",
    "777": "19",
    "2980": "\u0120consider",
    "3115": "\u0120times",
    "3968": "Fl",
    "4062": "\u0120quick",
    "2747": "orage",
    "3793": "emplate",
    "474": "ack",
    "660": "ated",
    "48": "Q",
    "2778": "\u0120search",
    "1097": "\u0120am",
    "79": "p",
    "2562": "mt",
    "2193": "tract",
    "3343": "\".",
    "3285": "\u0120sever",
    "3360": "Null",
    "2634": "}\u010d\u010a\u010d\u010a",
    "1820": "the",
    "2398": "path",
    "4080": "pc",
    "3854": "\u0120pack",
    "1473": ":\u010a\u010a",
    "3500": "}}",
    "443": "\u0120//",
    "603": "\u0120us",
    "1844": "Un",
    "1572": "ines",
    "2146": "(&",
    "3609": "unic",
    "3025": "\u0120able",
    "3039": "room",
    "4051": "\u0120decl",
    "2786": "ality",
    "1307": "arget",
    "1220": "its",
    "1837": "HE",
    "1215": "ner",
    "1452": "ULL",
    "2869": "\u0120techn",
    "3608": "\u0120ident",
    "1063": "\u0120some",
    "1511": "\u0120used",
    "1829": "IM",
    "3463": "\u0120thought",
    "1068": "view",
    "1629": "\u0120run",
    "400": "\u0120$",
    "3069": "entity",
    "1862": "\u0120support",
    "162": "\u00e6",
    "3863": "iple",
    "2216": "\u0120really",
    "80": "q",
    "3122": "\u0120bas",
    "3521": "\u0120exc",
    "1568": "try",
    "1004": "[i",
    "1260": "ible",
    "4070": "\u00e2\u0122\u013bve",
    "3000": "\u0120db",
    "3904": "iment",
    "2596": "oney",
    "717": "12",
    "3735": "\u0120Pol",
    "3868": "\u0120wait",
    "381": "----",
    "1793": "odule",
    "4043": "\u0120ess",
    "3804": "\u0120Sub",
    "189": "\u0101",
    "823": "ield",
    "2509": "ought",
    "887": "\u0120id",
    "1594": "face",
    "3430": "\u0120price",
    "2064": "\u0120sw",
    "971": "cho",
    "1001": "lement",
    "3740": "OUT",
    "2359": "ready",
    "151": "\u00db",
    "1678": "til",
    "3773": "cover",
    "2955": "\u0120design",
    "2171": "ret",
    "2626": "\u0120business",
    "194": "\u0106",
    "2422": "quals",
    "2": "#",
    "4050": "Var",
    "2825": "\u0120'./",
    "3640": "ged",
    "925": "\u0120string",
    "727": "ery",
    "2333": "\u0120incre",
    "1358": "\u0120array",
    "1437": "\u0120br",
    "2855": "(R",
    "898": "public",
    "1439": "ures",
    "1422": "\u0120dif",
    "2173": "Of",
    "1000": "indow",
    "2199": "\u0120page",
    "3515": "\u0120having",
    "1211": "Object",
    "2048": "table",
    "1119": "roll",
    "1515": "\u0120log",
    "3482": "patch",
    "476": "ublic",
    "419": "==",
    "1730": "Size",
    "3174": "41",
    "1283": "\u0120He",
    "3118": "\u0120present",
    "1280": "\u0120ind",
    "2355": "\u0120\u0120\u010a",
    "294": "\u0120d",
    "1713": "oken",
    "787": "oint",
    "3499": "chema",
    "2905": "\u0120Log",
    "1323": "\u0120rem",
    "2823": "icro",
    "1906": "\u0120mark",
    "2472": "\u0120map",
    "183": "\u00fb",
    "2524": ".Size",
    "3669": "AGE",
    "230": "\u012a",
    "3747": "/**",
    "1679": "();\u010d\u010a",
    "1738": "File",
    "701": "\u0120your",
    "3397": "andle",
    "1672": "\u0120ins",
    "2306": "\u0120happ",
    "413": "turn",
    "4052": "(err",
    "607": "ail",
    "3604": "\u0120actually",
    "3545": "ral",
    "203": "\u010f",
    "1436": "\u0120could",
    "1869": "miss",
    "1660": "etail",
    "3754": "\u0120news",
    "465": "\u0109\u0109\u0109\u0109",
    "4069": "INE",
    "1982": "ook",
    "2068": "\u0120program",
    "2771": "\u0120sure",
    "3623": "\u0120Co",
    "1435": "ager",
    "1138": "arr",
    "752": "ep",
    "652": "pr",
    "3429": "\u0120para",
    "3690": "amed",
    "1061": "Data",
    "3455": "change",
    "3003": "\u0120init",
    "943": "new",
    "1181": "\u0120char",
    "2886": "\u0120gre",
    "2927": ".js",
    "2600": "ublish",
    "1564": "uto",
    "1727": "alk",
    "3419": "\u0120pot",
    "1959": "Over",
    "3175": "width",
    "2458": "\u0120tot",
    "3268": "\u0120rights",
    "415": "\u0120\u0120\u0120\u0120\u0120",
    "491": "elf",
    "1533": "\u0120(!",
    "3557": "ias",
    "1303": "ting",
    "3145": "ols",
    "1715": "\u0120request",
    "1540": "orn",
    "2446": ".to",
    "1722": "\u0120echo",
    "622": "\u0120J",
    "3676": "\u0120React",
    "2346": "\u0120coun",
    "2274": "\u0120develop",
    "3021": "\u0120love",
    "2211": "\u0120ca",
    "2014": "Context",
    "433": "\u0120it",
    "417": "res",
    "278": "al",
    "1913": "\u0120fin",
    "1382": "order",
    "1963": "\u0120index",
    "680": "app",
    "1174": "\u0120,",
    "2779": "ken",
    "4047": "ball",
    "335": "\u0120}",
    "1123": "idth",
    "3027": "AX",
    "2896": "ottom",
    "1756": "ync",
    "3244": "\u00c3\u00b3n",
    "67": "d",
    "904": "\u0120any",
    "2913": "IZ",
    "3757": "cel",
    "1976": "raph",
    "1274": "\u0120people",
    "3621": "\u0120happen",
    "1479": "cription",
    "3566": "\u0120web",
    "1423": "State",
    "1232": "':",
    "432": "\u0120R",
    "279": "\u0120the",
    "3369": "\u0120eff",
    "4017": "\u0120limit",
    "429": "=\"",
    "3730": "':\u010a",
    "449": "\u0120with",
    "2221": "tra",
    "184": "\u00fc",
    "2898": "PT",
    "1552": "_h",
    "1585": "Event",
    "2939": "\u0120Fr",
    "2266": ".\"\u010a\u010a",
    "722": "_m",
    "3743": "\u0120-->\u010a",
    "2527": "start",
    "870": ".h",
    "665": "\u0120en",
    "1589": "\u0120cr",
    "1363": ">\u010a\u010a",
    "1421": "\u0120rec",
    "2394": "\u0120Pr",
    "163": "\u00e7",
    "3551": ".state",
    "3279": "\u0120Ed",
    "1190": ".j",
    "2230": "iled",
    "2534": "iron",
    "2189": "())",
    "1962": "not",
    "1689": "\u0120bel",
    "3342": "emp",
    "395": "ass",
    "1353": "\u0120loc",
    "3490": "\u00e3\u0122\u0124\u010a\u010a",
    "991": "\u0120em",
    "2709": "\u0120os",
    "2671": "\u0120options",
    "1158": "\")\u010a",
    "2393": "\u0120console",
    "2349": "\u0120change",
    "2019": "\u0120say",
    "3195": "way",
    "3243": "\u0120win",
    "1821": "ants",
    "2367": "Hand",
    "2592": "\u0120source",
    "2846": "'m",
    "3991": "_string",
    "1731": "rawing",
    "2742": "lean",
    "2438": "rl",
    "650": "\u0120V",
    "161": "\u00e5",
    "2425": "\u0120iss",
    "860": "View",
    "3112": "And",
    "1457": "\u0120now",
    "896": "roup",
    "2801": "info",
    "2933": "au",
    "2347": "obj",
    "3650": "\u0120prob",
    "531": "ert",
    "1524": "\u0120even",
    "526": "ang",
    "1861": "').",
    "950": "ical",
    "2290": "\u0120None",
    "3093": "ored",
    "1376": "\u0120form",
    "910": "nder",
    "2938": "ORT",
    "1062": "\u0120val",
    "2822": "No",
    "1983": "uck",
    "3390": "iddle",
    "1528": "(d",
    "2988": "\u0120func",
    "2821": "pen",
    "142": "\u00d2",
    "1173": "\u0120},\u010a",
    "3047": ":\"",
    "2264": "signed",
    "2313": "({\u010a",
    "4008": "ili",
    "2130": "ift",
    "262": "\u0120\u0120\u0120",
    "235": "\u012f",
    "966": "30",
    "838": "val",
    "2297": "\u00d1\u0123",
    "296": "\u0120m",
    "2646": "\u0120never",
    "1042": "ponse",
    "1371": "unc",
    "5": "&",
    "1390": "\u0120want",
    "468": "\u0120W",
    "756": "',\u010a",
    "3716": "fa",
    "942": "son",
    "3637": "\u0120store",
    "495": "ult",
    "323": "\u0120and",
    "1652": "\u0120cal",
    "3451": "\u0120\u00e2\u0122\u013a",
    "3143": "OP",
    "2326": "\u0120US",
    "612": "\u0120&",
    "3377": "Builder",
    "102": "\u00a9",
    "3415": "vo",
    "748": "\u0109if",
    "1784": "/**\u010a",
    "1922": "\u0120cre",
    "3348": "(g",
    "3043": "ike",
    "3212": "imer",
    "836": "\u0120name",
    "4091": "anger",
    "3425": "\u0120\u0120\u0120\u0120\u0120\u0120\u0120\u0120\u0120\u0120\u0120\u0120\u0120\u0120\u0120\u0120\u0120\u0120\u0120\u0120\u0120\u0120\u0120\u0120\u0120\u0120\u0120\u0120\u0120\u0120\u0120\u0120\u0120\u0120\u0120\u0120\u0120\u0120\u0120\u0120\u0120\u0120\u0120",
    "2796": "mission",
    "387": "\u0120be",
    "1595": "\u0120`",
    "236": "\u0130",
    "2110": "tings",
    "1267": "_M",
    "2411": "ium",
    "4003": "ictionary",
    "2079": "request",
    "1807": "_data",
    "3237": "\u0120express",
    "254": "\u0142",
    "1702": "_B",
    "2568": "Count",
    "1723": "function",
    "4073": "\u0120Us",
    "361": "ue",
    "40": "I",
    "2371": "04",
    "929": ".l",
    "2312": "ln",
    "3808": "ements",
    "131": "\u00c7",
    "2513": "state",
    "2222": "ingle",
    "3346": "\u0120percent",
    "3974": "\u0120live",
    "2185": "www",
    "1555": "\u0120through",
    "2580": "js",
    "3334": "rior",
    "3086": "\u0120});\u010a\u010a",
    "2353": "los",
    "2526": "])",
    "3072": "\u0120option",
    "3572": ".on",
    "3890": "ensor",
    "1450": "\u0120hand",
    "2667": "_set",
    "164": "\u00e8",
    "492": "ight",
    "2538": "iction",
    "932": "_C",
    "708": "so",
    "3511": "Bar",
    "3881": "\u0120apply",
    "3859": "\u0120unsigned",
    "857": "pan",
    "599": "yst",
    "1550": "\u0120did",
    "4081": "loor",
    "825": "Cont",
    "2655": "\u0120intern",
    "555": "\u0120by",
    "767": "\u0120var",
    "2565": "\u0120block",
    "2058": "iter",
    "4057": "fort",
    "1010": "ception",
    "113": "\u00b5",
    "3914": "cast",
    "2439": "ons",
    "2374": "System",
    "886": "\";\u010a",
    "3518": "abs",
    "1994": "ene",
    "3076": "69",
    "3041": "\u0120give",
    "2908": "ament",
    "422": "\u0120if",
    "445": "\u0120L",
    "2557": "uint",
    "3227": "(),\u010a",
    "1166": "ponent",
    "1148": "\u0120what",
    "968": "(f",
    "3723": "\u0120United",
    "2826": "acy",
    "140": "\u00d0",
    "3406": "(j",
    "2520": "For",
    "3698": "\u0120comb",
    "3161": "\u0120With",
    "2032": "loy",
    "2031": "70",
    "2332": "sw",
    "1191": "lection",
    "606": "one",
    "1038": "\u010a\u010a\u010a\u010a",
    "1841": "\u0120car",
    "2930": "\u0120online",
    "974": "ose",
    "1544": "27",
    "2325": "_v",
    "2815": "\u0120die",
    "1667": "\u0120years",
    "1293": "erson",
    "291": "ed",
    "2739": "ru",
    "221": "\u0121",
    "405": "->",
    "365": "ew",
    "2145": "\u0120vis",
    "1328": "\u0120__",
    "2022": "\u0120className",
    "1903": "\u0120made",
    "2763": "\u0120lot",
    "2150": "title",
    "2899": "status",
    "2194": "ane",
    "78": "o",
    "1992": "enter",
    "2912": "icy",
    "3817": "lin",
    "532": "ial",
    "1624": "\u0120del",
    "2961": "\u0120arr",
    "1081": "\u0120comm",
    "1596": "_A",
    "3800": "(true",
    "3211": ".v",
    "1336": "wh",
    "2392": "tes",
    "3183": "apper",
    "619": "ould",
    "2608": "])\u010a",
    "625": "ign",
    "3582": "\u0120though",
    "3236": "year",
    "325": "se",
    "1198": "\u0120--",
    "1039": "lock",
    "693": "return",
    "3895": "IO",
    "3431": "ury",
    "1241": "\u0109public",
    "726": "self",
    "267": "st",
    "3234": "\u0120Do",
    "3688": "tributes",
    "487": "::",
    "1484": "99",
    "771": "ink",
    "2497": "local",
    "872": "\u0120their",
    "3541": "\u0120fre",
    "2034": "sg",
    "384": "\u0120e",
    "2400": "dition",
    "3485": "\u0120above",
    "2108": "usiness",
    "735": "\u0120K",
    "1309": "olumn",
    "423": "\u0120D",
    "1916": "eger",
    "3642": "Us",
    "3915": "From",
    "1856": "\u0120Pl",
    "282": "\u0120f",
    "843": "32",
    "3434": "\u0120'/",
    "3654": "\u0120${",
    "3171": "ounds",
    "3438": "Ph",
    "408": "end",
    "3851": "\u0120application",
    "1431": "\u00e2\u0122\u013bt",
    "1501": "\u0120show",
    "421": "\u0120wh",
    "2977": "Http",
    "3484": "\u00e3\u0124",
    "2725": ".find",
    "2911": "\u0120children",
    "2564": "\u0120...",
    "2620": "Table",
    "2051": "Prop",
    "133": "\u00c9",
    "842": "\u0120end",
    "1152": "olum",
    "2727": "me",
    "1443": "\u0120Sh",
    "1009": "ove",
    "1691": "21",
    "2648": "arse",
    "1397": "\u0120require",
    "1866": "\u0120own",
    "3140": ".sw",
    "2406": "_L",
    "228": "\u0128",
    "1721": "01",
    "1365": "\"]",
    "2569": "open",
    "2499": "};\u010a",
    "759": "atch",
    "4046": "\u0120\u00c3\u00a9",
    "1176": "\u0120first",
    "1618": "\u0120here",
    "1090": "Int",
    "2126": "\u0120cour",
    "1811": "\u00e3\u0122\u0124",
    "2953": "admin",
    "1350": "),\u010a",
    "1432": "\u010a\u010a\u010a",
    "3732": "\u00d0\u00b0\u00d0",
    "3132": "\u0120[]",
    "137": "\u00cd",
    "2485": "https",
    "1661": "\u0120num",
    "3685": "\u0120expected",
    "3866": "Vector",
    "1531": "else",
    "2640": "///",
    "632": "ount",
    "1145": "],",
    "1824": "-c",
    "3245": "\u0120thing",
    "930": "ource",
    "1408": "\u0120\u0120\u0120\u0120\u0120\u0120\u0120\u0120\u0120\u0120\u0120\u0120\u0120\u0120\u0120\u0120\u0120\u0120\u0120\u0120\u0120\u0120\u0120\u0120\u0120\u0120\u0120\u0120\u0120\u0120\u0120",
    "3011": "\u0120That",
    "3207": "\u00e2\u0122\u013bre",
    "3131": "\u0120once",
    "3407": "Sc",
    "1264": "sum",
    "2770": "SON",
    "3768": "ocal",
    "2177": "ross",
    "265": "re",
    "3647": "sm",
    "166": "\u00ea",
    "3020": "elper",
    "259": "\u0120t",
    "450": "iz",
    "447": "qu",
    "3470": "\u0109break",
    "1920": "\u0120process",
    "124": "\u00c0",
    "319": "\u010d\u010a",
    "1295": "ote",
    "2567": "\u0120keep",
    "938": "\u0120ro",
    "2089": "PO",
    "3340": "ued",
    "3205": "iod",
    "2301": "ency",
    "2113": "api",
    "3668": "(\"#",
    "2293": "format",
    "1240": ")\u010d\u010a",
    "3616": "ULT",
    "1221": "\u0120Con",
    "3293": "\u0120recent",
    "2119": "col",
    "840": ".f",
    "171": "\u00ef",
    "258": "in",
    "3995": "\u0120young",
    "3401": "\u0120$_",
    "1299": "ular",
    "1022": "\u0120off",
    "1043": "\u0120sup",
    "3257": "ograph",
    "917": "\u0120app",
    "523": "\u0120ch",
    "3600": "\u0120services",
    "435": "\u0120F",
    "1391": "\u0120comp",
    "3948": "ught",
    "3910": "GL",
    "4042": "ico",
    "2372": "\u0120gover",
    "2047": "\u0120prop",
    "616": "ell",
    "821": "_d",
    "1631": "ym",
    "456": "get",
    "1411": "ood",
    "1904": "true",
    "144": "\u00d4",
    "1454": "();\u010a\u010a",
    "1366": "aph",
    "2348": ".php",
    "242": "\u0136",
    "12": "-",
    "3568": "\u0120deal",
    "2680": "\u0120access",
    "261": "er",
    "559": "\u0120sh",
    "2844": "uted",
    "3776": "\u0120black",
    "1598": "ature",
    "1546": "tn",
    "994": "\u0120when",
    "1720": "\u0120}\u010d\u010a",
    "3408": "Width",
    "1441": "ets",
    "1918": "iness",
    "3645": "\u0120format",
    "3606": "Empty",
    "2838": "%%",
    "853": "ange",
    "504": "\u0120\u0120\u0120\u0120\u0120\u0120\u0120\u0120\u0120\u0120\u0120\u0120\u0120\u0120\u0120\u0120\u0120\u0120\u0120",
    "2850": "ari",
    "284": "\u0120=",
    "3468": "\u0120Min",
    "3782": "\u0120came",
    "186": "\u00fe",
    "639": "\u0120\u00e2\u0122",
    "1798": "\u0120inst",
    "1399": "60",
    "392": "ub",
    "2073": "\u0120und",
    "3050": "iversity",
    "882": "user",
    "587": "ak",
    "3733": "float",
    "3437": "ymb",
    "1638": "list",
    "2117": "oto",
    "2915": "ably",
    "2615": ".push",
    "2345": "\u00e2\u0122\u0136",
    "906": "we",
    "3762": "\u0109\u0120",
    "174": "\u00f2",
    "226": "\u0126",
    "2017": "over",
    "4004": "urther",
    "900": "umber",
    "141": "\u00d1",
    "3384": "ished",
    "1006": ".F",
    "1345": ".M",
    "1412": "uch",
    "87": "x",
    "2805": "pons",
    "237": "\u0131",
    "2088": "ilter",
    "3191": "cribe",
    "150": "\u00da",
    "3662": "\u0120>>",
    "1045": "date",
    "2937": "\u0120instance",
    "0": "!",
    "3414": "ITY",
    "1512": "cept",
    "75": "l",
    "47": "P",
    "2440": "\u0120label",
    "2232": "Qu",
    "3010": "\u0120later",
    "441": "ke",
    "4025": ".z",
    "654": "row",
    "1327": "\u0120ext",
    "2559": "\u0120stand",
    "3728": "\u0120global",
    "1683": "atter",
    "2837": "point",
    "3327": "\u0120expl",
    "1343": "\u0120ph",
    "108": "\u00b0",
    "1579": "\u0120high",
    "740": "\u0120*/\u010a",
    "3108": "(){\u010a",
    "2030": "\u0120But",
    "3371": "\u0120tell",
    "1781": "\u0120think",
    "3659": "_of",
    "2142": "utes",
    "1500": "></",
    "378": "\u00e2\u0122",
    "2735": "ML",
    "1650": "\u0120call",
    "65": "b",
    "461": "ore",
    "2885": "\");\u010d\u010a",
    "1688": "At",
    "1330": "pace",
    "1034": "\u0120%",
    "3289": "\u0120enc",
    "2884": "\u0120done",
    "3603": "params",
    "807": "bject",
    "1703": "\u0120:=",
    "3380": "esc",
    "1100": "yp",
    "1218": "\u0120ent",
    "3843": "istr",
    "2761": "\u0120der",
    "317": ");\u010a",
    "1165": "////////",
    "3314": "\u0120State",
    "1285": "ful",
    "3981": "eme",
    "444": "con",
    "1098": "rol",
    "993": "\u0120sp",
    "1777": "PE",
    "3483": "annot",
    "1487": "\u0120std",
    "2167": "\u0120direct",
    "1970": ".Windows",
    "1657": "\u0120});\u010a",
    "978": "\u00c3\u00a9",
    "3924": ".H",
    "851": "_id",
    "3351": "\u0120move",
    "2861": "\u0120*/\u010a\u010a",
    "4086": "tx",
    "2964": "page",
    "3589": "ptr",
    "1137": "ense",
    "1308": "RO",
    "3583": "leep",
    "716": "per",
    "1035": "**\u010a",
    "21": "6",
    "4010": "yl",
    "1302": "bs",
    "1389": "\u0120\u00e2\u0122\u0135",
    "3156": "\u0120until",
    "1186": "\u0109f",
    "2551": "(_",
    "3708": "\u0120send",
    "2378": "Up",
    "2098": "\u0120ref",
    "2289": "\u0120extends",
    "539": "\u0120not",
    "2285": "json",
    "3214": "Sub",
    "54": "W",
    "3671": "edit",
    "3148": "\u0120mass",
    "2104": "\u0120provid",
    "3601": "pg",
    "2295": "inter",
    "1857": "_type",
    "1069": "\u0120pe",
    "3300": "\u0120money",
    "458": "ile",
    "1474": "-m",
    "2388": "_V",
    "1601": "ister",
    "959": "var",
    "239": "\u0133",
    "1517": "fl",
    "2577": "\u0120Bo",
    "2155": "\u0120writ",
    "1337": "type",
    "2382": "ero",
    "913": "param",
    "2666": "(r",
    "1005": "\u0120use",
    "552": "ies",
    "2046": "\u0120week",
    "3321": "\u0120window",
    "3666": "\u0120typ",
    "3203": "<T",
    "1163": "Ch",
    "3672": "QL",
    "2614": "68",
    "1542": "Se",
    "951": "\u0120des",
    "1927": "36",
    "1064": "fter",
    "3413": "Module",
    "1075": "/*",
    "1248": "irect",
    "177": "\u00f5",
    "57": "Z",
    "280": ";\u010a",
    "2081": "escription",
    "1078": "\u0120\u0120\u0120\u0120\u0120\u0120\u0120\u0120\u0120\u0120\u0120\u0120\u0120",
    "4089": "ymbol",
    "4082": "FT",
    "2658": "mod",
    "2315": "ases",
    "3767": "ERROR",
    "1054": "\u0120\u00e2\u0122\u013e",
    "2714": "Config",
    "572": "iew",
    "1584": "\u0120line",
    "545": "();\u010a",
    "3510": "isc",
    "1256": "Item",
    "2887": ".Re",
    "2144": "\u0120fact",
    "4014": "rest",
    "2341": "//\u010a",
    "2239": "book",
    "2690": "aps",
    "407": "ction",
    "3919": "ny",
    "3761": "@\"",
    "3805": "\u0120air",
    "1536": "\u0120ob",
    "3680": "\u0120RE",
    "3975": "temp",
    "1129": "://",
    "1817": "\u0120check",
    "2554": "pi",
    "2413": "\u0120wom",
    "2950": ".\u00e2\u0122\u013f\u010a\u010a",
    "3825": "pend",
    "245": "\u0139",
    "805": "ser",
    "1335": "action",
    "1355": "-s",
    "1464": "\u0120break",
    "2654": "Ad",
    "589": "ath",
    "3387": "OW",
    "579": "ide",
    "1805": "vice",
    "1591": "28",
    "1420": "(this",
    "2807": "\u0120ver",
    "2277": "ading",
    "2265": "ric",
    "2038": "\u0120information",
    "446": "(\"",
    "3596": "\u0120ever",
    "2251": "ference",
    "2804": "\u0120perform",
    "2583": "Status",
    "403": "port",
    "1128": "Con",
    "310": "\u0120\u0120\u0120\u0120\u0120\u0120\u0120\u0120\u0120\u0120\u0120",
    "1751": "ott",
    "2983": "42",
    "3193": "\"/",
    "100": "\u00a7",
    "3282": "\u00c3\u00a3",
    "2373": "\u0120version",
    "2647": "Response",
    "2589": "07",
    "859": "ator",
    "3561": "Reg",
    "82": "s",
    "1373": "\u0120read",
    "2625": "([",
    "332": "ut",
    "4023": "ival",
    "2931": "imal",
    "2015": "\u0120order",
    "554": "ure",
    "962": ".d",
    "3839": "\u0120track",
    "1262": "\u0120org",
    "85": "v",
    "1622": "Key",
    "1789": "\u0120For",
    "1114": "17",
    "1776": "\u0120sl",
    "3878": "\u0120terms",
    "2231": "\u0120put",
    "1627": "26",
    "1395": "be",
    "2563": "\u0120Bl",
    "1349": "ersion",
    "3950": "posed",
    "2165": "meric",
    "2545": "09",
    "105": "\u00ac",
    "3284": "\u0120possible",
    "3556": "while",
    "761": "\",\u010a",
    "3892": "\u0120several",
    "41": "J",
    "2343": "\u0120pay",
    "472": "art",
    "3963": "avel",
    "1326": ".g",
    "792": "\u0120\u0120\u0120\u0120\u0120\u0120\u0120\u0120\u0120\u0120\u0120\u0120\u0120\u0120\u0120\u0120\u0120\u0120\u0120\u0120\u0120\u0120\u0120\u0120\u0120\u0120\u0120\u0120\u0120\u0120\u0120\u0120",
    "1291": "ier",
    "3746": "oss",
    "1140": "cess",
    "3988": "uly",
    "393": "\u0120P",
    "1588": "itial",
    "3630": "\u0120info",
    "3956": "\u0120products",
    "2777": "\u0120boolean",
    "302": "ct",
    "1704": "_w",
    "3547": "\u0120fac",
    "3880": "-r",
    "191": "\u0103",
    "2738": "oogle",
    "2730": "#endif",
    "10": "+",
    "1440": "\u0120know",
    "1948": "\u0120top",
    "3900": "\u0120il",
    "1438": "ends",
    "3809": "(id",
    "3046": "ators",
    "3954": "\u0120}}",
    "3167": "\u0120mus",
    "2760": "ploy",
    "3822": "essages",
    "135": "\u00cb",
    "2799": "oad",
    "1498": "ql",
    "287": "ing",
    "644": "In",
    "328": "\u0120S",
    "2370": "aving",
    "3543": "\u0120complet",
    "3571": "position",
    "1593": "cause",
    "3701": "TH",
    "1041": "100",
    "673": ".get",
    "3354": ".To",
    "1499": "\u0120pol",
    "1714": "amespace",
    "1077": "\u0120her",
    "1767": "Info",
    "3613": "\u0120conc",
    "1490": "80",
    "1831": "OT",
    "1852": ".Drawing",
    "3753": "198",
    "295": "et",
    "2676": "ety",
    "2303": "oy",
    "3998": "\u0120Prop",
    "1677": "mon",
    "3188": "imary",
    "3194": "\u0120miss",
    "3154": "\u0120aut",
    "3886": "witter",
    "209": "\u0115",
    "3692": "Source",
    "249": "\u013d",
    "3447": "ids",
    "2160": "\u0120ret",
    "2957": "une",
    "1838": "\u0120Res",
    "2578": "printf",
    "3830": "\u0120box",
    "2817": "../../",
    "3790": "\u0120handle",
    "426": "\u0120B",
    "4053": "LECT",
    "2575": "True",
    "1368": "erty",
    "3177": "\u0120light",
    "2492": "aces",
    "2500": "\u0120another",
    "2521": "ior",
    "4033": "\u0120official",
    "2287": "66",
    "1951": "De",
    "1712": "time",
    "396": "int",
    "1444": ".w",
    "1561": "\u0120New",
    "3693": "(string",
    "2971": "/c",
    "3905": "Rec",
    "132": "\u00c8",
    "3563": "Start",
    "1197": "ock",
    "1112": "UL",
    "437": "os",
    "134": "\u00ca",
    "2831": "Content",
    "3591": "++;\u010a",
    "507": "\u0120O",
    "3618": "\";\u010d\u010a",
    "813": "\u0120his",
    "2307": "\u0120super",
    "356": "\u0120C",
    "3686": "\u0120yet",
    "3760": "Default",
    "1143": "ument",
    "2161": "osition",
    "3005": "\u0120She",
    "326": "\u0120l",
    "512": ":\u010a",
    "238": "\u0132",
    "3644": "_index",
    "1848": ".Form",
    "2757": "ired",
    "3022": "quote",
    "1394": "az",
    "1701": "\u0120using",
    "902": "\u0120which",
    "3494": "\u0120Return",
    "2308": "bar",
    "2558": "\u0120produ",
    "2910": "inc",
    "2907": "\u0120),\u010a",
    "1222": "ouble",
    "2745": "ording",
    "4087": "\u0120pur",
    "885": ".A",
    "742": "\u0120void",
    "1917": "\u0120world",
    "2724": "\u0120User",
    "1790": "\u0120much",
    "99": "\u00a6",
    "3262": "/m",
    "2737": "\u0120including",
    "3153": "ips",
    "1680": "):",
    "2891": "ANT",
    "1527": "from",
    "3287": "\u0120didn",
    "970": "value",
    "1357": "\u0120Int",
    "1372": "ET",
    "139": "\u00cf",
    "4049": "inding",
    "641": "cc",
    "786": "abel",
    "1912": "\u0120group",
    "2710": ".name",
    "1880": "\u0120et",
    "784": "ss",
    "330": "\u0120\"",
    "1804": "px",
    "401": ";\u010a\u010a",
    "800": "\u0120St",
    "3059": "ze",
    "3184": "ollections",
    "3797": "_sh",
    "899": "vel",
    "2003": "oin",
    "3907": "\u0120University",
    "3959": "\u0120Des",
    "3231": "base",
    "2192": "ai",
    "1659": "formation",
    "3993": "itude",
    "1553": "iver",
    "288": "es",
    "832": "\u0120one",
    "3764": "(value",
    "3926": "\u0120Fe",
    "3826": "dir",
    "2657": "(data",
    "3226": "57",
    "3121": "uest",
    "769": "Id",
    "720": "\u0120\u010a",
    "2542": "gress",
    "1902": "alth",
    "3862": "\u00c4\u00b1",
    "1339": "ait",
    "2401": "_to",
    "2391": "\u0120during",
    "869": "ov",
    "1877": "\u0120sex",
    "28": "=",
    "4022": "\u0120sizeof",
    "3882": "\u0120session",
    "3546": "\\x",
    "386": "\u0120M",
    "3110": "\u0120ID",
    "145": "\u00d5",
    "116": "\u00b8",
    "719": "\u0120but",
    "3147": "\");\u010a\u010a",
    "1294": "ION",
    "1522": "\u0120pass",
    "339": "th",
    "2055": ".\u010a\u010a\u010a\u010a",
    "3376": "oper",
    "834": "\u0120dis",
    "1908": "ified",
    "2588": "location",
    "2414": "left",
    "640": "aram",
    "2052": "\u0120All",
    "3538": "ause",
    "2716": "ERR",
    "3127": "\u0120lib",
    "331": "ch",
    "2619": "atrix",
    "583": "rou",
    "3410": "atform",
    "2839": "03",
    "647": "ong",
    "1537": "\u0120item",
    "1300": "\u00e3\u0122",
    "3305": "\u00ef\u00bb\u00bf",
    "4085": ")->",
    "679": "201",
    "3984": "\u0120provided",
    "3281": "\u0120dest",
    "2540": "acter",
    "3015": "ILE",
    "3989": "auto",
    "478": "est",
    "122": "\u00be",
    "1427": "\u0120look",
    "3341": "\u0120Car",
    "3082": "\u0120True",
    "2901": "uments",
    "3977": "\u0120variable",
    "3169": "\u0120kind",
    "684": "ition",
    "2919": "\u0120days",
    "788": "ous",
    "1898": "Service",
    "4020": "\u0120cou",
    "3584": "\u0120<!--",
    "1478": "ocument",
    "2862": "ope",
    "2356": "Le",
    "3443": "400",
    "1933": "\u0120color",
    "2249": "ux",
    "3970": "\u0120seen",
    "2904": ":\u010d\u010a",
    "486": "ere",
    "3631": "_tr",
    "2506": ".I",
    "3758": "login",
    "388": "ers",
    "3464": "_con",
    "3627": "Grid",
    "3592": ".png",
    "1099": "\u0120gr",
    "2633": "\u0120govern",
    "2692": "ained",
    "3477": "\u0120review",
    "2461": "ification",
    "1428": "AM",
    "2642": "af",
    "3073": "\u0120exist",
    "63": "`",
    "3689": "atis",
    "2973": "irtual",
    "1177": "');\u010a",
    "953": "ix",
    "668": "te",
    "3899": "achine",
    "4038": "\u0120months",
    "743": "\u0120set",
    "2186": "},",
    "980": "oll",
    "3291": "\u0120],\u010a",
    "704": "\u0120out",
    "637": "rr",
    "2688": "Not",
    "3535": "rary",
    "948": "].",
    "3536": "ades",
    "584": "\u0120we",
    "402": "av",
    "1980": "?\u010a\u010a",
    "1559": "ouse",
    "2602": "_pro",
    "1988": "\u0120input",
    "29": ">",
    "2816": "\u0120site",
    "485": "ind",
    "2663": "\u0120called",
    "3310": "udio",
    "2948": "(a",
    "3404": "Token",
    "986": "ames",
    "2940": "where",
    "1606": "\u0120because",
    "2712": "_G",
    "3774": "\u0120UI",
    "1516": "ution",
    "3549": "\u0120created",
    "3507": "\u0120IS",
    "2941": "\u0120javax",
    "3180": "ohn",
    "728": "ft",
    "1860": "\u0120av",
    "3498": "\u0120publish",
    "366": "\u0120<",
    "794": "\":",
    "3960": ".path",
    "1122": "ian",
    "818": "ne",
    "2662": "\u0120/>\u010a",
    "2968": "ability",
    "1635": "_N",
    "1059": "raw",
    "256": "\u0120\u0120",
    "3792": "Back",
    "3938": "\u0120future",
    "2618": "47",
    "878": "OR",
    "2102": ".append",
    "566": "cl",
    "1759": "urs",
    "3710": "unsigned",
    "1639": "ited",
    "574": "\u0120was",
    "1654": "\u0120dec",
    "3871": "\u0120together",
    "1656": "oun",
    "3559": "\u0120);\u010a\u010a",
    "24": "9",
    "614": "div",
    "3933": "fs",
    "527": "\u0120are",
    "428": "ext",
    "3290": "\u0120command",
    "1212": "\u0120start",
    "1113": "ating",
    "1025": "';\u010a",
    "2674": "Point",
    "1460": "ackage",
    "2587": "\u0120custom",
    "301": "el",
    "1879": "\u0120sign",
    "890": "_b",
    "30": "?",
    "1929": "AG",
    "1065": "ys",
    "3094": "\u0120step",
    "933": "]\u010a",
    "2419": "orth",
    "1882": "','",
    "246": "\u013a",
    "2733": "\u0120feel",
    "1931": "img",
    "496": "str",
    "2728": "\u0120given",
    "3217": "\u0120experience",
    "3667": "dev",
    "1188": "ient",
    "2726": ".org",
    "3058": "thers",
    "4026": "Link",
    "2107": "\u0120cap",
    "1673": "aint",
    "1592": "\u0120tem",
    "3250": "\u0120doesn",
    "2377": "Style",
    "1239": "\u0120reg",
    "3033": "});\u010a",
    "2827": "rec",
    "1514": "\u0120play",
    "4012": "OK",
    "1481": "-b",
    "780": "atic",
    "3364": "/*\u010a",
    "2140": "\u0120Cont",
    "2553": "ormal",
    "1636": "ared",
    "3253": "\u0109g",
    "3456": "\u0120\u0120\u0120\u0120\u0120\u0120\u0120\u0120\u0120\u0120\u0120\u0120\u010a",
    "2340": "\u0120Americ",
    "1448": "\u0120fr",
    "314": "\u0120{",
    "3917": "\u0120subject",
    "649": "\u0120can",
    "822": "io",
    "515": "--------",
    "3168": "iff",
    "1571": "igned",
    "549": "\u0120U",
    "2268": "!\u010a\u010a",
    "3315": "da",
    "4036": "\u0120received",
    "1316": "day",
    "3141": "eb",
    "2845": "\u00e3\u0125",
    "2170": "As",
    "2810": "Util",
    "4035": "olve",
    "1845": "\u0120bool",
    "2960": "\u0120cent",
    "3734": "\u0120except",
    "2023": "pany",
    "3400": "\u0120Cal",
    "984": "AL",
    "1348": "fore",
    "2711": "ension",
    "2820": "\u0120})\u010a",
    "1987": "38",
    "1867": "\u0120cor",
    "3766": "\u0120previous",
    "3835": "\u0120msg",
    "1785": "FF",
    "779": "\u0120so",
    "753": "\u00e2\u0122\u013bs",
    "3799": "\u0120Dec",
    "757": "\u0120me",
    "1108": "igh",
    "2481": "eters",
    "3479": "move",
    "2584": "Instance",
    "3893": "ii",
    "642": "\u0120*/",
    "148": "\u00d8",
    "119": "\u00bb",
    "2431": "erg",
    "880": "tem",
    "3652": "()\u010d\u010a",
    "3529": "/d",
    "947": "];\u010a",
    "1210": ".\"",
    "1229": "\u0120Q",
    "3523": "plied",
    "2420": "${",
    "3814": "\u0120night",
    "3309": "\u0120told",
    "406": "nt",
    "346": "ce",
    "2210": "ervices",
    "2200": "hip",
    "3816": "\u0120Red",
    "1941": "bers",
    "2991": "\u0120Text",
    "2993": "(function",
    "889": "\u0120who",
    "3570": "Integer",
    "1261": "loat",
    "1451": "Ind",
    "1139": "\u0120into",
    "3729": "\u0120contact",
    "272": "\u0120c",
    "977": "ater",
    "2387": "(l",
    "1505": "\u0120find",
    "3254": "\u0120single",
    "1590": "ars",
    "602": "\u0120i",
    "646": "_s",
    "167": "\u00eb",
    "1182": "CT",
    "483": "ine",
    "530": "_t",
    "2523": "\u0120fun",
    "2094": "akes",
    "4075": "mark",
    "2033": "\u0120double",
    "3612": "style",
    "3896": "\u0120template",
    "2570": "\u0120['",
    "1842": "ypes",
    "1746": "\u0120($",
    "2259": "ina",
    "2305": "\u0120month",
    "340": ")\u010a",
    "772": "lect",
    "1735": "object",
    "730": "////",
    "524": "</",
    "1626": "thing",
    "923": "\u0120add",
    "1854": "ision",
    "3845": "ube",
    "3861": "\u0120One",
    "1466": "ren",
    "3104": "active",
    "528": "\u0120int",
    "1037": "ade",
    "1919": "ty",
    "1718": "lob",
    "2043": "\"></",
    "2836": "adi",
    "3909": "\u0120\u0120\u0120\u0120\u0120\u0120\u0120\u0120\u0120\u0120\u0120\u0120\u0120\u0120\u0120\u0120\u0120\u0120\u0120\u0120",
    "3785": "oding",
    "2695": "-w",
    "3109": "\u0120government",
    "3013": "df",
    "3252": "ging",
    "1204": "[\"",
    "1806": "37",
    "212": "\u0118",
    "2696": "\u0120Date",
    "2641": "ts",
    "3497": "ustr",
    "2321": "Em",
    "2546": ".size",
    "2539": "\u0120full",
    "1770": ".e",
    "2375": "nect",
    "1086": "ethod",
    "884": "com",
    "718": "ich",
    "585": "ject",
    "3294": "olution",
    "1742": "\u0120style",
    "2556": "!--",
    "1529": "\u0120bl",
    "3368": "py",
    "2963": "len",
    "698": "ple",
    "883": "\u0120)",
    "2951": "ODE",
    "1400": "\u0120col",
    "452": "\u0120N",
    "196": "\u0108",
    "3223": "alt",
    "18": "3",
    "3573": "\u0120(\"",
    "1605": "other",
    "1017": "itle",
    "1083": "min",
    "2682": "\u0120protected",
    "3454": "obile",
    "793": "RE",
    "1213": "file",
    "424": "ver",
    "3695": "ites",
    "944": "ern",
    "436": "\u0120r",
    "3789": "\u0120root",
    "2947": "\u0120Mar",
    "3417": ".Data",
    "2722": "\u0120Te",
    "2075": "75",
    "2493": "\u0120Cl",
    "2921": "rect",
    "618": "err",
    "1786": "ool",
    "1510": "\u0120current",
    "360": "ul",
    "3014": "UG",
    "1556": "\u0120An",
    "2537": "\u0120los",
    "2541": "board",
    "2294": "\u0120great",
    "1769": "imes",
    "1975": "....",
    "34": "C",
    "1304": "\u0120make",
    "2204": "\u0120different",
    "3016": "\u0120client",
    "37": "F",
    "1893": "\u0120create",
    "3986": "\u0120filename",
    "808": "essage",
    "1640": "olog",
    "110": "\u00b2",
    "1018": "rit",
    "1797": "\u0120count",
    "2254": "\u0120local",
    "22": "7",
    "3048": "\u0120copy",
    "596": "'s",
    "2661": "ugg",
    "1072": "du",
    "3292": "_x",
    "3719": "\u0120become",
    "1578": "\u0120again",
    "2975": "_url",
    "3232": "(name",
    "3412": "\u0120hold",
    "342": "\u0120g",
    "2715": "aff",
    "3179": "Row",
    "595": "))",
    "2791": "ether",
    "3080": "67",
    "3182": "vironment",
    "2996": "down",
    "3506": "color",
    "1008": "\u0120ad",
    "683": "ory",
    "915": "fig",
    "1238": "ices",
    "2890": "\u0120health",
    "819": "ish",
    "4093": "ecess",
    "1554": "\u0120sm",
    "3478": "('/",
    "2205": "iable",
    "537": "ost",
    "498": "\",",
    "3452": "\u0120?>",
    "1324": "ptions",
    "2490": "ories",
    "3711": "FA",
    "2040": "\u0120oper",
    "1681": "Set",
    "916": ".com",
    "2860": "\u0120total",
    "2606": "\u0120mill",
    "3810": "\u0120enter",
    "690": "\u0120will",
    "3585": "\u0120points",
    "3489": "\u0120Qu",
    "3133": "center",
    "3233": "ones",
    "677": "ob",
    "1028": "\u0120te",
    "1208": "\u0120la",
    "3158": "\u0120area",
    "2441": ".y",
    "3206": "\u0120Mon",
    "2396": "ves",
    "2475": ".$",
    "710": "ax",
    "3712": "\u0120params",
    "1642": "Box",
    "2299": "iving",
    "2042": "db",
    "1788": "qual",
    "2487": "\u0120ear",
    "2424": "_size",
    "826": "ings",
    "2841": "erved",
    "2183": "\u0120exper",
    "2253": "_e",
    "3560": "\u0120role",
    "4065": "utions",
    "2609": "\u0120chang",
    "2868": "uro",
    "72": "i",
    "213": "\u0119",
    "439": "\u0120as",
    "1644": "33",
    "2943": "apter",
    "104": "\u00ab",
    "1532": "\u00d0\u00b5",
    "1914": "\u0120License",
    "345": ",\u010a",
    "1415": "arent",
    "2027": "\u0120product",
    "1989": "\u0120art",
    "4056": "\u0120~",
    "1375": "\u0120rel",
    "225": "\u0125",
    "3128": "Property",
    "815": ".S",
    "2250": "Log",
    "358": "\u0120I",
    "3363": "\u0120city",
    "797": "eg",
    "901": "ble",
    "3759": "heet",
    "357": "\u0120st",
    "1378": "Exception",
    "2762": "resent",
    "2803": "Arg",
    "2842": "viron",
    "3857": "\u0120section",
    "3190": "\u0120camp",
    "1937": "OM",
    "2070": "ape",
    "182": "\u00fa",
    "2187": "\u0120allow",
    "2502": "ogle",
    "3481": "ERT",
    "181": "\u00f9",
    "2463": "\u0120tri",
    "2830": "\"))",
    "3488": "\u0120question",
    "3034": ".Com",
    "3424": "\u0120property",
    "2566": "Input",
    "17": "2",
    "2122": "Result",
    "3574": "\u00e4\u00b8",
    "2694": "\u0120sum",
    "3265": "unch",
    "1446": "\u0120ser",
    "2225": "\u0120both",
    "2893": "\u0120Be",
    "2412": "';\u010a\u010a",
    "3503": "allback",
    "1761": "./",
    "839": "led",
    "1342": "text",
    "1082": "ise",
    "1472": "\u0120You",
    "3331": "\u0120General",
    "268": "en",
    "2958": "\u0120File",
    "86": "w",
    "2245": ".data",
    "1870": "ually",
    "4029": "\u0120community",
    "920": ".D",
    "1774": "45",
    "264": "\u0120a",
    "931": "000",
    "3099": "struction",
    "3840": "');\u010a\u010a",
    "3803": "'=>",
    "817": "use",
    "1416": "\u0120/*",
    "1489": "Time",
    "538": "\u0120class",
    "337": "ol",
    "1619": "ined",
    "1095": "\u0120let",
    "3620": "uary",
    "50": "S",
    "3665": "\u0120save",
    "908": "\u0120li",
    "608": "====",
    "816": "\u0120Y",
    "3794": "\u0120getting",
    "2351": "'re",
    "127": "\u00c3",
    "372": "um",
    "3031": "req",
    "3903": "elt",
    "307": "id",
    "3440": "\u0120attack",
    "1765": "\u0120sur",
    "3870": "\u00c3\u00a5",
    "2843": "IF",
    "955": "\u0120type",
    "1910": "yn",
    "1690": "\u0120many",
    "3124": "child",
    "3442": "ROM",
    "551": "\u0120:",
    "3349": ":(",
    "2280": "namespace",
    "3971": "51",
    "2769": "_ex",
    "2127": "An",
    "146": "\u00d6",
    "868": "15",
    "1455": "\u0120most",
    "327": "ex",
    "2920": "reated",
    "2965": ",'",
    "3958": "\u0120bad",
    "1426": "_F",
    "795": "olor",
    "2453": "ram",
    "1840": "\u00d0\u00b8",
    "1014": "\u0120\u0120\u0120\u0120\u0120\u0120\u0120\u0120\u0120\u0120\u0120\u0120\u0120\u0120\u0120\u0120\u0120\u0120\u0120\u0120\u0120\u0120\u0120\u0120\u0120\u0120\u0120",
    "159": "\u00e3",
    "2529": "\u0120},",
    "1268": "\u0120how",
    "518": "',",
    "349": "ate",
    "3610": "\u0120million",
    "2918": "erial",
    "3192": "255",
    "849": "Ex",
    "2512": "\u0120care",
    "1768": "par",
    "1582": "uthor",
    "3987": "\u0120hope",
    "2781": "\u0120er",
    "2864": "UM",
    "376": "tr",
    "320": "\u0120(",
    "3096": "CK",
    "379": "\u0120y",
    "2336": "ways",
    "1386": "uff",
    "2856": "\u0120offic",
    "1225": "very",
    "525": "ave",
    "2766": "\u0120bit",
    "2776": ".pro",
    "292": "ic",
    "205": "\u0111",
    "2270": "ived",
    "699": "ild",
    "3029": "\u00c3\u00b6",
    "3578": "ABLE",
    "2457": "\u0120date",
    "1758": "35",
    "3367": "inary",
    "2470": "num",
    "3113": "\u0120display",
    "973": "utton",
    "1900": "ats",
    "4000": ">();\u010a",
    "2591": "\u0120\u010d\u010a",
    "3166": "IV",
    "3324": "\u0109t",
    "1828": "\u0120next",
    "1577": "(int",
    "1020": "().",
    "88": "y",
    "3304": ".\u010d\u010a",
    "2599": "AP",
    "481": "able",
    "888": "read",
    "3476": "ports",
    "3562": "\u0120Color",
    "3230": "\u0120specific",
    "3457": "ici",
    "534": "}\u010a",
    "1370": "\u0120par",
    "3336": "IB",
    "633": "}\u010a\u010a",
    "298": "\u0109\u0109",
    "4015": "\u0120ST",
    "305": "\u0120h",
    "550": "\u0120pr",
    "2756": "apt",
    "1160": "\u0120list",
    "1488": "\u0120fil",
    "2415": "ources",
    "2644": "istory",
    "83": "t",
    "2639": "urch",
    "3807": "nav",
    "1319": "(p",
    "802": "\u0120ar",
    "2376": "response",
    "3836": "fect",
    "3946": "ires",
    "1597": "Button",
    "1462": "._",
    "1612": "\u0120dist",
    "1265": "_in",
    "1185": "={",
    "891": "\">\u010a",
    "2252": "post",
    "2090": "\u0109this",
    "229": "\u0129",
    "1617": "att",
    "1581": "Index",
    "3516": "lem",
    "2256": "assert",
    "1907": "rid",
    "4083": "\u0120opp",
    "1048": "\u0120bu",
    "416": "lic",
    "4076": "\u0120Name",
    "2041": "ced",
    "3629": "\u0120often",
    "49": "R",
    "3846": "\u0120ce",
    "3875": "host",
    "9": "*",
    "2631": "\u0120required",
    "2783": "EM",
    "1369": "\u0120Se",
    "3399": "\u0120ben",
    "897": "rop",
    "1091": "ask",
    "1278": "(m",
    "3681": ".put",
    "659": "\u0120self",
    "3032": "Client",
    "1470": "\u0109c",
    "451": "de",
    "1007": "pec",
    "1847": "\u0120game",
    "11": ",",
    "2257": "Val",
    "3486": "itive",
    "1534": "ized",
    "664": "ud",
    "1322": "\u0120Pro",
    "3004": "quired",
    "2455": "())\u010a",
    "3103": "Stream",
    "2547": "\u0120body",
    "2495": "78",
    "1015": "atus",
    "473": "\u0120H",
    "3159": "uit",
    "309": "am",
    "1736": "ince",
    "1580": "html",
    "2719": "#if",
    "3599": "('#",
    "3215": "\u0120button",
    "3887": "\u0120fund",
    "1899": "UN",
    "2148": "31",
    "425": "age",
    "1611": "\u0120De",
    "2226": "Override",
    "3847": "itted",
    "2895": "\u0120Gr",
    "1695": "\u0120good",
    "1292": "_name",
    "3952": "\u0120took",
    "3705": "comm",
    "3475": "\u0120Test",
    "3136": "\u0120continue",
    "2800": "\u0120rest",
    "1046": "\u0120acc",
    "669": "_c",
    "2465": "my",
    "324": "ur",
    "1029": "ml",
    "2234": "ung",
    "3185": "\u0120side",
    "1647": "\u0120mon",
    "1836": "\u0120includ",
    "1310": "rc",
    "3173": "_key",
    "1106": "_P",
    "581": "ib",
    "4016": "icrosoft",
    "2935": "control",
    "3844": "(S",
    "2240": "creen",
    "1716": "\u0120child",
    "621": "pon",
    "569": "ard",
    "1747": "Model",
    "3317": "));\u010a\u010a",
    "711": "\u0120def",
    "2751": "\u0120got",
    "1972": "\u0120real",
    "2060": "uration",
    "1648": "\u0120way",
    "1231": "ttp",
    "3028": "\u0120Copyright",
    "121": "\u00bd",
    "3255": "offset",
    "2797": "AME",
    "3247": "\u0120THE",
    "1859": "nection",
    "2875": "\u0120short",
    "3980": "\u0120ge",
    "2218": "\u0120target",
    "385": "lo",
    "4079": "amic",
    "3639": "\u0120What",
    "3301": "INT",
    "972": "18",
    "499": "\u0120you",
    "2622": "]);\u010a",
    "3969": "\u0120exec",
    "2835": "\u0120video",
    "1311": "_re",
    "2390": "ATE",
    "927": "\u0120over",
    "2050": "place",
    "2670": "\u0120};\u010a",
    "2982": "\u0120Array",
    "147": "\u00d7",
    "3879": "framework",
    "2522": "\u0120Sc",
    "2693": "atur",
    "1334": "air",
    "2488": "################",
    "1969": "mand",
    "471": "\u0120return",
    "1131": "...",
    "852": "urre",
    "3558": "BUG",
    "2645": "Str",
    "3319": "\u0120query",
    "3769": "\u0120material",
    "1883": "\u0120App",
    "3874": "'))",
    "3095": "ances",
    "347": "od",
    "1545": "ample",
    "2576": "\u0120url",
    "666": "\u0120Th",
    "1526": "uild",
    "1049": "200",
    "3316": "msg",
    "1697": "ational",
    "494": "orm",
    "3045": "client",
    "2020": "static",
    "2629": "ta",
    "2056": ".R",
    "2561": "\u0120available",
    "3550": "uper",
    "3806": "ops",
    "497": "..",
    "1930": "valid",
    "3280": "\u0120season",
    "1105": "ors",
    "4094": "efined",
    "1896": ".in",
    "1352": "ateg",
    "578": "\u0120The",
    "2552": "yles",
    "2612": "\u0120output",
    "3326": "agn",
    "877": "LE",
    "1247": "ek",
    "2923": "irm",
    "3246": "Trans",
    "2331": "\u0120]",
    "222": "\u0122",
    "1405": "\u0120where",
    "3783": "\u0120delete",
    "2452": ".sh",
    "2018": "\u0120contin",
    "2444": "anel",
    "207": "\u0113",
    "2223": "ital",
    "3634": "\u0120space",
    "3936": "Title",
    "2515": "\u0120effect",
    "1551": "wn",
    "3450": "\u0120mom",
    "1013": "ader",
    "3375": "imum",
    "620": "ull",
    "2510": ".Cont",
    "3770": "\u0120below",
    "1135": "50",
    "2873": "\u0120seem",
    "1773": "-d",
    "3151": "omic",
    "1418": "\u0120while",
    "1762": "pre",
    "3260": "\u0120anal",
    "2914": "ands",
    "232": "\u012c",
    "1915": "Field",
    "1167": "\u0120z",
    "1849": "rows",
    "2421": "88",
    "2159": "ond",
    "380": "ist",
    "420": "\u0120this",
    "2752": "stand",
    "1682": "29",
    "3248": "\u0120<?",
    "303": "nd",
    "879": "\u0120private",
    "3288": "\u0120sent",
    "2632": "_R",
    "3911": "icture",
    "2684": "\u0120There",
    "1060": "\u0120year",
    "1794": "\u0120som",
    "643": "ER",
    "1459": ">\u010d\u010a",
    "1812": "\u0120med",
    "799": "ude",
    "2536": "\u0120non",
    "3199": "omain",
    "3393": "\u0120async",
    "3196": "\u0120based",
    "1711": "uring",
    "3018": "ffer",
    "1429": "ility",
    "1344": "\u0120fl",
    "3235": "\u0120along",
    "3125": "ifier",
    "3165": "\u0120Sp",
    "1132": "arch",
    "3791": "CC",
    "3722": "\u0120diff",
    "691": "IN",
    "3524": "ao",
    "4032": "Ref",
    "149": "\u00d9",
    "1865": "\").",
    "671": "\u0120ab",
    "2881": "irl",
    "695": "data",
    "4021": "ogn",
    "1325": "vid",
    "2233": "\u00d1\u0122",
    "2149": "Al",
    "3997": "\u0120website",
    "3009": "\u0120stop",
    "845": "16",
    "169": "\u00ed",
    "3100": "(C",
    "3824": "\u0120dam",
    "4054": "One",
    "3496": "\u00c3\u00a3o",
    "2775": "header",
    "2790": "46",
    "2675": "You",
    "3576": "sv",
    "190": "\u0102",
    "1796": "\u0120List",
    "1620": "\u0120final",
    "3679": "\u0120redu",
    "1940": "\u0120sk",
    "1254": "\u0120Wh",
    "2504": "ework",
    "789": "eld",
    "2178": "();",
    "480": "\u0120G",
    "1050": "\u0120Re",
    "2829": "\u0109\u0120\u0120\u0120",
    "3534": "97",
    "1281": "\u0120jav",
    "627": ".\u010a",
    "2543": "\u0120turn",
    "1458": "rough",
    "2573": "Action",
    "874": "irst",
    "2765": "\u0109d",
    "2736": "\u0120already",
    "682": "\u0120all",
    "1026": "ms",
    "3202": "UP",
    "562": "ption",
    "4061": "Check",
    "1417": "\u0120arg",
    "1935": "\u0120take",
    "638": "ome",
    "3694": "\u0120+\u010a",
    "2507": "NS",
    "96": "\u00a3",
    "3433": "roy",
    "3441": "\u0120Ste",
    "576": "this",
    "750": "ally",
    "1070": "\u0120there",
    "1053": "\u0120would",
    "1286": "ole",
    "1513": "clud",
    "969": "ra",
    "175": "\u00f3",
    "945": "\u0120ag",
    "3941": "\u0120mode",
    "1509": "enu",
    "3355": "\u0120vi",
    "1565": "ler",
    "3224": "\u0120country",
    "3007": "react",
    "3581": "anch",
    "2275": "\u00d0\u00be\u00d0",
    "217": "\u011d",
    "3114": "\u00d0\u00bb",
    "2774": "erties",
    "3008": "\u0120ann",
    "92": "}",
    "1934": "\u0120report",
    "2976": "argin",
    "1055": "ven",
    "1699": ".log",
    "2638": "\u0120Set",
    "2215": "\u0120rece",
    "3458": "na",
    "3944": "\u0120ax",
    "2508": "ology",
    "2114": "OD",
    "1492": "\u0120->",
    "3781": "stit",
    "1169": "let",
    "3403": "\u0120enough",
    "1685": "\u0120pres",
    "907": "\u0120value",
    "1154": "ages",
    "2753": "\u0120less",
    "1073": "of",
    "670": "uct",
    "2214": "ration",
    "594": "\u0120res",
    "2237": "\u0120level",
    "2300": "Ent",
    "3614": "ios",
    "3210": "ively",
    "3449": "\u0120meet",
    "1924": "ives",
    "215": "\u011b",
    "2246": "\u0120document",
    "2316": "\u0120title",
    "3328": "itter",
    "1645": "\u0120ac",
    "996": "\u0120\u0120\u0120\u0120\u0120\u0120",
    "3649": "\u0120details",
    "253": "\u0141",
    "2995": "\u0120eng",
    "1230": "php",
    "3278": "\u0120women",
    "573": "\u0109\u0109\u0109",
    "389": "\u0120on",
    "404": "ir",
    "241": "\u0135",
    "2746": "If",
    "3898": "\u0120econ",
    "861": "List",
    "949": "\u0120?",
    "180": "\u00f8",
    "4063": "\"),",
    "1739": "uf",
    "1936": "rib",
    "2327": "UI",
    "128": "\u00c4",
    "2143": "atab",
    "1403": "\u0120two",
    "15": "0",
    "2999": "\u0120Dr",
    "3934": "false",
    "1889": "code",
    "4048": "\u0120learn",
    "477": "\u0120or",
    "3391": "43",
    "3707": ")\u010a\u010a\u010a",
    "1321": "cond",
    "3702": "=True",
    "2535": "Label",
    "785": "own",
    "371": "ort",
    "136": "\u00cc",
    "3663": "\u0120face",
    "1120": "\u0120just",
    "2005": "ui",
    "2998": "\u0120En",
    "2247": "\",\"",
    "758": "\u0120!",
    "582": "ac",
    "2871": "IR",
    "2384": "endif",
    "1763": "\u0120)\u010a",
    "1467": "#define",
    "3469": "\u0120opt",
    "1192": "))\u010a",
    "3339": "\u0120making",
    "3586": "\u0120\u0120\u0120\u0120\u0120\u0120\u0120\u0120\u0120\u0120\u0120\u0120\u0120\u0120\u0120\u0120\u0120\u0120\u0120\u0120\u0120\u0120\u0120\u0120\u0120",
    "1340": "<?",
    "33": "B",
    "1810": "idd",
    "1891": "\u0120di",
    "383": "he",
    "3579": "ATION",
    "3795": "_by",
    "2617": "ination",
    "1109": "\u0120than",
    "1202": "\u0120its",
    "661": "ary",
    "536": "ode",
    "463": "\u0120pro",
    "3493": "\u0120provide",
    "1996": ".length",
    "120": "\u00bc",
    "4090": "uation",
    "3427": "go",
    "3164": "\"><",
    "2574": "\u0120things",
    "3588": "\u0120::",
    "382": ".\u010a\u010a",
    "2720": "uction",
    "1271": "To",
    "655": "ber",
    "3787": "rops",
    "3208": "\u0120lik",
    "2874": "\u0120q",
    "1795": "\u0120http",
    "55": "X",
    "153": "\u00dd",
    "3053": "\u0120Can",
    "1873": "ience",
    "4001": "ional",
    "3325": "\u0120least",
    "2310": "_de",
    "1305": "Tr",
    "367": "ation",
    "89": "z",
    "2969": "outh",
    "3699": "items",
    "2798": "\u0120temp",
    "1754": "\u0120()",
    "760": "\">",
    "3748": "ilit",
    "2972": "pose",
    "2123": "Code",
    "2456": "\u0120(\u010a",
    "1706": "lish",
    "2866": "ights",
    "2101": "aining",
    "706": "\u0120has",
    "3405": ".user",
    "3297": "\u0120May",
    "2021": ".Text",
    "3160": "\u0120length",
    "2330": "\u0120[\u010a",
    "1818": "ween",
    "1195": "mer",
    "623": "_p",
    "2857": "ks",
    "3916": "ales",
    "2978": "\u0120school",
    "1539": "UR",
    "781": "\u0120lo",
    "1643": "ife",
    "2934": "Url",
    "1149": "anc",
    "989": "ely",
    "3312": "\u0120equ",
    "3749": "\u0120Event",
    "3378": "IP",
    "1518": "\u0120see",
    "362": "\u0120A",
    "2501": "<<",
    "1925": "\u0120main",
    "2176": "ee",
    "322": "//",
    "3078": "vers",
    "2892": "()\u010a\u010a",
    "3070": "\u0120family",
    "3216": "\u0120Up",
    "714": "alse",
    "3811": "anged",
    "2974": "earch",
    "1669": "IS",
    "778": "cont",
    "2560": "\u0120proble",
    "3973": "\u0120border",
    "60": "]",
    "648": "ie",
    "1413": "ative",
    "73": "j",
    "281": "\u0120p",
    "3163": "event",
    "3218": "CL",
    "3872": "\u0120throws",
    "2758": "\u0120Add",
    "2100": "\u0120So",
    "3370": "ario",
    "1496": "roller",
    "617": "\u0120have",
    "2889": "rist",
    "3542": "\u0120'@",
    "850": "error",
    "1088": "ute",
    "1187": "24",
    "2263": ".print",
    "1986": "ivers",
    "2686": "\u0120address",
    "3622": "\u0120server",
    "2808": "lib",
    "3714": "ros",
    "1663": "query",
    "8": ")",
    "434": "ess",
    "956": "'t",
    "547": "ime",
    "2164": "args",
    "2012": "////////////////",
    "2158": "ftware",
    "2292": "(String",
    "1263": "und",
    "2994": "null",
    "2630": "field",
    "2001": "\u0120\u00e2\u0122\u0136",
    "3337": "EX",
    "3964": "(:",
    "1872": "std",
    "200": "\u010c",
    "359": "un",
    "2511": ">>",
    "1246": ".G",
    "3142": "\u0120Public",
    "1146": "wo",
    "3347": "\u0120past",
    "1404": "\u0120size",
    "293": "\u0120b",
    "3750": "curity",
    "1284": "_st",
    "3625": "\u0120les",
    "1549": "gram",
    "3962": "\u0120Post",
    "3658": "\u0120Free",
    "3992": "btn",
    "2811": "Listener",
    "1124": "\u0120them",
    "3897": "Position",
    "3395": "cul",
    "1668": "Color",
    "3703": "\u0120bar",
    "1766": "\u0120found",
    "2007": "\u0120table",
    "2906": "erver",
    "2115": "\u0120field",
    "731": "ake",
    "873": "')",
    "2408": "imit",
    "3526": "\u0120++",
    "3739": "i\u00c3\u00b3n",
    "1615": "\u0120cons",
    "1576": "lear",
    "3638": ",\u010a\u010a",
    "2404": "etwork",
    "1030": "co",
    "179": "\u00f7",
    "2138": "\u0120fam",
    "2013": ".util",
    "1895": "Array",
    "3350": "\u0120write",
    "856": "\u0120my",
    "990": "\u0120work",
    "3374": "level",
    "2703": "_path",
    "1094": "ody",
    "806": "11",
    "3221": "\u0120near",
    "3137": "\u0120talk",
    "3420": "\u0120Trump",
    "751": "set",
    "2718": "ately",
    "1333": "stance",
    "4028": "\u0120across",
    "333": "if",
    "3778": "\u0120American",
    "1341": "IC",
    "3942": "\u0120'<",
    "1815": "ache",
    "3063": "\u0120lead",
    "738": "\u0120const",
    "390": "\u0120con",
    "1087": ".P",
    "629": ");\u010a\u010a",
    "3867": "byte",
    "1675": "\u0120sim",
    "1985": "test",
    "1523": "\u0120down",
    "269": "or",
    "3928": "unit",
    "1196": ".W",
    "3181": "alf",
    "3060": "\u0120either",
    "1482": "\u00d0\u00be",
    "64": "a",
    "4068": "\u0120comment",
    "227": "\u0127",
    "1787": "plate",
    "686": "ear",
    "2207": "_IN",
    "1801": ".id",
    "2082": "\u0120code",
    "3480": "\u0120switch",
    "3075": "\u0120Object",
    "3323": "only",
    "2687": "\u0120uint",
    "2997": "\u0120include",
    "2834": "\u0120won",
    "1687": "We",
    "3271": "aper",
    "2550": "199",
    "2093": "\u0120===",
    "4006": "ALL",
    "2480": "uid",
    "2002": "ten",
    "3054": "ounc",
    "3261": "create",
    "2317": "\u0120context",
    "2106": "med",
    "2360": "\u0120No",
    "1538": "ump",
    "1351": ".re",
    "2832": "_W",
    "828": "\u0120data",
    "3335": "\u0120record",
    "1560": "\u0120es",
    "3038": "_com",
    "101": "\u00a8",
    "1468": "itt",
    "3537": "_se",
    "1287": "){\u010a",
    "2109": "\u0120rep",
    "3786": "\u0120card",
    "3362": "IZE",
    "1728": "lication",
    "170": "\u00ee",
    "2664": "body",
    "954": "ays",
    "1495": "\u0120text",
    "2708": "\u0120appe",
    "1228": "lick",
    "2613": "\u0120email",
    "1066": "\u0120///",
    "464": ";\u010d\u010a",
    "3923": "What",
    "2851": "\u0120player",
    "875": "ick",
    "2334": "script",
    "3388": "\u0120course",
    "1772": "\u0120post",
    "3084": "_time",
    "724": "quest",
    "1102": "\u0120It",
    "3833": "rel",
    "3296": "\u0120By",
    "605": "10",
    "3501": "\u0120CON",
    "2744": "\u0120always",
    "1868": "count",
    "1707": "\u0120stud",
    "2773": "\u0120prom",
    "91": "|",
    "3697": "\u0120members",
    "657": "ll",
    "676": "ress",
    "2946": "59",
    "1258": ".st",
    "1171": "red",
    "2074": "ategory",
    "3902": "main",
    "56": "Y",
    "3023": "oud",
    "1888": "\u0120best",
    "2471": "Act",
    "1709": "\u0120gu",
    "2528": "vious",
    "941": "Type",
    "2196": "context",
    "881": "\u010d\u010a\u010d\u010a",
    "1871": "\u0120mem",
    "3935": "unt",
    "611": "\u0120/",
    "2133": "\u0120going",
    "734": "\u0120function",
    "1236": ".L",
    "1475": "\u0120every",
    "1874": "search",
    "773": "ug",
    "1346": "ccess",
    "3540": "\u0120*/\u010d\u010a",
    "1469": "\u0120ap",
    "2338": "\u0120src",
    "3229": "\u0120author",
    "713": "ge",
    "3052": "{{",
    "1803": "\u0120gener",
    "1289": "opy",
    "1406": "UT",
    "2368": "};\u010a\u010a",
    "1961": "\u0120\u0120\u0120\u0120\u0120\u0120\u0120\u0120\u0120\u0120\u0120\u0120\u0120\u0120\u0120\u0120\u0120\u0120\u0120\u0120\u0120\u0120\u0120\u0120\u0120\u0120\u0120\u0120\u0120\u0120\u0120\u0120\u0120\u0120\u0120",
    "3258": "ley",
    "733": "\u0120go",
    "2072": ".Forms",
    "3784": "property",
    "4039": "\u0120anim",
    "1878": "ename",
    "1168": "\u0120kn",
    "2096": "44",
    "1616": "rint",
    "2447": "\u0120project",
    "3358": "'ll",
    "2925": "omb",
    "3939": "ached",
    "3700": "\u0120Per",
    "2181": "It",
    "98": "\u00a5",
    "796": "tp",
    "3673": "\u0120items",
    "2518": "ending",
    "2324": "\u0120life",
    "2517": "_file",
    "138": "\u00ce",
    "2409": "With",
    "1977": "\u0120build",
    "936": "ca",
    "2627": "height",
    "3947": "There",
    "204": "\u0110",
    "2700": "\u0120port",
    "1116": "ref",
    "1465": "\u0120);\u010a",
    "4044": "87",
    "2628": ".html",
    "2120": "(x",
    "3514": "ourn",
    "871": "\u0120>",
    "1607": "roid",
    "1993": "ground",
    "2269": "-f",
    "2743": "outer",
    "1995": "\u00c3\u00a1",
    "837": "\u0120true",
    "2281": "_O",
    "567": "##",
    "3751": "ster",
    "3269": "(M",
    "1255": "Bo",
    "3951": "icult",
    "1710": "config",
    "999": "quire",
    "553": "ize",
    "1205": "\u0120need",
    "2366": "202",
    "1189": "cent",
    "1740": "ffect",
    "1932": "PI",
    "634": "dd",
    "2679": "\u0120ide",
    "2598": "\u0120partic",
    "2586": "\u0120come",
    "1201": "ank",
    "3913": "cer",
    "1749": "\u0120method",
    "178": "\u00f6",
    "1184": "ople",
    "2065": "ization",
    "3539": "\u0120employ",
    "848": "log",
    "3738": "\u0120certain",
    "3569": "++)\u010a",
    "2878": "Group",
    "1543": "man",
    "3994": "Attribute",
    "1826": "\u0120est",
    "1802": "aking",
    "1966": "On",
    "564": "ok",
    "1600": "ES",
    "2754": "/s",
    "725": "odel",
    "2004": "\u0120ke",
    "3435": "\u0120polit",
    "2637": ".,",
    "2213": "App",
    "2011": "\u0120must",
    "3311": "current",
    "1967": ";\u010d\u010a\u010d\u010a",
    "1298": "rror",
    "3117": "\u0120far",
    "2416": "atri",
    "855": "rray",
    "2403": "\u0120against",
    "2478": "\u0120few",
    "521": "ase",
    "1753": "ING",
    "3918": "password",
    "3660": "(false",
    "517": "{\u010a",
    "160": "\u00e4",
    "3313": "\u0120auto",
    "3611": "\u0120aff",
    "2132": "\u0120second",
    "1733": "\u0120\u0120\u0120\u0120\u0120\u0120\u0120\u0120\u0120\u0120\u0120\u0120\u0120\u0120\u0120\u0120\u0120",
    "2361": "\u0120position",
    "3074": "ica",
    "707": "String",
    "2668": "ird",
    "2105": "\u0120assert",
    "1814": "ider",
    "812": "ents",
    "1979": "assword",
    "2124": ".is",
    "3002": "side",
    "791": "The",
    "3146": "\u0120**",
    "715": "ON",
    "3509": "imate",
    "985": "using",
    "3088": "egin",
    "663": "']",
    "112": "\u00b4",
    "27": "<",
    "2188": "\u0120\u00c2",
    "3446": "\u0120story",
    "3123": "echo",
    "529": "\u00e2\u0122\u013b",
    "352": "ay",
    "835": "AT",
    "2812": "arge",
    "4095": "........",
    "2209": "\u0120Is",
    "522": ".c",
    "1036": "ann",
    "2049": "idget",
    "1541": "\u0120don",
    "219": "\u011f",
    "520": "\u0120at",
    "2328": "ocation",
    "2169": "Pl",
    "2172": "ado",
    "2095": "Controller",
    "2659": "annel",
    "273": "le",
    "2916": "\u0120distrib",
    "1483": "][",
    "2405": "\u0120Ph",
    "3320": "\u0120Br",
    "2706": "aim",
    "2979": "ava",
    "2956": "\u0120Data",
    "831": "fo",
    "765": "\u0120|",
    "220": "\u0120",
    "2383": "\u0120law",
    "23": "8",
    "2318": "08",
    "709": "\u0120up",
    "1755": "\u0120expect",
    "2137": "39",
    "866": "clude",
    "1778": "\u0120such",
    "3345": "\u0120close",
    "3432": "\u0120today",
    "3961": "'\u010a\u010a",
    "2385": "\u0120base",
    "2362": "\u0120old",
    "2759": "\u0120account",
    "1079": "Res",
    "820": "old",
    "2792": "posit",
    "3344": "\u0120Med",
    "540": "og",
    "354": "ot",
    "3111": "ajor",
    "1301": "\u0120\u00d0",
    "2071": "check",
    "1665": "\u0120object",
    "3812": "End",
    "2585": "\u0120control",
    "1134": "\u0120<<",
    "4011": "istance",
    "411": "ith",
    "1726": "Element",
    "2045": "icle",
    "363": "ow",
    "316": "om",
    "2879": "section",
    "940": "ual",
    "1651": "\u0120att",
    "240": "\u0134",
    "442": "rom",
    "636": "\u0120get",
    "2279": "UE",
    "1921": "(b",
    "3090": "\u0120water",
    "2084": "uffer",
    "2967": "\u0120bro",
    "2322": "\u0120met",
    "123": "\u00bf",
    "2852": "ais",
    "1950": "AS",
    "3628": "sql",
    "2731": "\u0120better",
    "3646": "most",
    "3225": "ibility",
    "457": "\u0120}\u010a",
    "2061": "older",
    "2057": "\u0120To",
    "1383": "By",
    "4077": "`\u010a",
    "2157": "\u0109m",
    "297": "\u0120o",
    "3057": "\u0120appro",
    "2136": "ness",
    "276": "an",
    "3655": "rypt",
    "2381": "init",
    "3945": "'];\u010a",
    "283": "ou",
    "2435": "\u0120They",
    "541": "ord",
    "290": "ion",
    "658": "\u0120el",
    "615": "ystem",
    "3201": "\u0120away",
    "3019": "POST",
    "3533": "_ID",
    "275": "it",
    "2203": "sp",
    "2701": "eh",
    "2121": "ght",
    "1183": "\u0120Tr",
    "1497": "lose",
    "460": "ata",
    "3597": "----------------------------------------------------------------",
    "173": "\u00f1",
    "2768": "\u0120following",
    "2489": "\u0120match",
    "2672": "\u0120Gener",
    "3077": "'ve",
    "2505": "TE",
    "1016": "Th",
    "3064": "attr",
    "32": "A",
    "2888": "\u0120belie",
    "3651": "\u0120AND",
    "2880": "max",
    "3097": "AY",
    "846": "cre",
    "3062": "\u0120important",
    "3187": "\u0120example",
    "77": "n",
    "1101": "\u0120also",
    "1155": "ayer",
    "1398": "\u0120Ex",
    "3949": "tml",
    "7": "(",
    "3865": "\u00d1\u0125",
    "508": "20",
    "1118": "\u0120static",
    "76": "m",
    "2755": "\u0120Ass",
    "1356": "trib",
    "3453": "\u0120den",
    "1984": "\u0120message",
    "3274": "empty",
    "1981": "\u00e2\u0122\u00a6",
    "2944": "\u0120reason",
    "1242": "SS",
    "2877": "ipp",
    "3155": ");\u010d\u010a\u010d\u010a",
    "1949": "\u0120free",
    "2010": "\u0120head",
    "867": "arg",
    "762": "ec",
    "533": "act",
    "2344": "plit",
    "3330": "\u0120column",
    "3725": "fully",
    "1393": "\u0120||",
    "3322": "auth",
    "467": "ain",
    "1257": "struct",
    "1250": "cript",
    "1107": "_n",
    "90": "{",
    "409": "\u0120de",
    "2243": "\u00e3\u0123",
    "1150": "Value",
    "3943": "_array",
    "1519": "indows",
    "38": "G",
    "1219": "\u0120Com",
    "1379": "input",
    "3755": "\u0120\",",
    "1433": "ayout",
    "3091": "\u0120che",
    "2749": "vis",
    "3850": "parent",
    "1": "\"",
    "2818": "EL",
    "3967": "\u0120known",
    "1126": "der",
    "93": "~",
    "1725": "ps",
    "1130": "ule",
    "858": "ict",
    "3525": "[$",
    "1558": "\u0120inv",
    "2451": "\u0109\u0109\u010a",
    "4088": "uel",
    "2683": "\u0120job",
    "313": "--",
    "3842": "\u0120John",
    "3352": "\u0120pat",
    "3385": "ills",
    "2732": "Page",
    "66": "c",
    "768": "ence",
    "3626": "\u0120files",
    "71": "h",
    "2848": "\u0120prof",
    "1269": "rite",
    "3332": "\":\"",
    "922": "\u0120about",
    "107": "\u00af",
    "2097": "Message",
    "336": "em",
    "1562": "export",
    "2652": "\u0120;",
    "1928": "_g",
    "1894": "ather",
    "519": "ant",
    "2224": "Layout",
    "3242": "\u0120imp",
    "2616": "\u0120}\u010d\u010a\u010d\u010a",
    "2399": "ialog",
    "1939": "Request",
    "588": "ve",
    "1641": "itch",
    "2103": "\u0120still",
    "1834": "content",
    "1347": "br",
    "2549": "eturn",
    "3460": "\u0120sort",
    "1693": "ender",
    "1816": "work",
    "1609": "ik",
    "1044": "++",
    "1449": "());\u010a",
    "662": "\u0120.",
    "1905": "AB",
    "801": "ound",
    "934": "\u0120qu",
    "1133": "ement",
    "459": "\u0120an",
    "3035": "erc",
    "2936": "irection",
    "905": "\u0120false",
    "1329": "')\u010a",
    "565": "__",
    "1947": "ollection",
    "208": "\u0114",
    "1946": "\u0120comple",
    "1360": "Pro",
    "2949": "\u0120within",
    "1832": "\u00c3\u00b3",
    "1127": "reak",
    "1093": "\u0120like",
    "25": ":",
    "130": "\u00c6",
    "1686": "array",
    "3996": ".txt",
    "3116": "\u0120four",
    "263": "on",
    "1563": "mary",
    "2235": "map",
    "2897": "\u0120args",
    "2484": "source",
    "1705": "ists",
    "3801": "\u0120comput",
    "1819": "\u0120((",
    "3602": "})\u010a",
    "575": "ip",
    "1520": "\u0120help",
    "158": "\u00e2",
    "2660": "\u0120np",
    "4092": "\u0120background",
    "2151": "\u0120android",
    "3276": "\u0120ant",
    "2044": "Param",
    "1649": "lete",
    "2174": "chn",
    "2066": "\u0109for",
    "1312": "define",
    "511": "oc",
    "2954": "ended",
    "829": "\u0120sa",
    "3402": "\u0120Rep",
    "2697": "\u0120little",
    "982": "yle",
    "2467": "\u0120Ad",
    "1923": "arn",
    "364": "\u0120'",
    "475": "import",
    "2984": "web",
    "3930": "\u0120du",
    "1737": "En",
    "3624": "SC",
    "1998": "(i",
    "3832": "(v",
    "3577": "\u0120press",
    "3955": "\u0120?>\u010a",
    "489": "\u0120+",
    "2932": ".con",
    "3149": "ured",
    "1180": "\u0120act",
    "2430": "\u0120width",
    "2339": "\u0120catch",
    "2813": "77",
    "2054": "box",
    "95": "\u00a2",
    "510": "\u0120[",
    "967": "enc",
    "3823": "\u0120human",
    "961": "\u0120part",
    "981": "pos",
    "1745": "_r",
    "2448": "\u00c3\u00bc",
    "613": "ach",
    "39": "H",
    "1943": ".Add",
    "391": "ap",
    "165": "\u00e9",
    "3594": "soft",
    "493": "('",
    "1318": "[]",
    "299": "ro",
    "2358": "({",
    "1157": "ues",
    "1387": "play",
    "3922": "\u00ef\u00bc\u012e",
    "2168": "oci",
    "1741": "AC",
    "3302": "bsite",
    "3066": "Equal",
    "3065": "ART",
    "3361": "\u0120special",
    "2483": "\u00c3\u0143",
    "3421": "idual",
    "700": "ther",
    "1117": "_S",
    "2445": "sc",
    "3056": "\u0120occ",
    "4066": "Base",
    "2854": "\u0120hum",
    "168": "\u00ec",
    "2689": "oo",
    "2604": "riter",
    "68": "e",
    "4072": "\u0120El",
    "1853": "\u0120path",
    "1973": "\u0120max",
    "1662": "aj",
    "2571": "\u0120throw",
    "937": "SE",
    "702": "\"\u010a",
    "2780": "\u0120orig",
    "2698": "\u0120fri",
    "1200": "\u0120op",
    "4060": "\u0120End",
    "946": "AR",
    "3619": "\u0120understand",
    "1012": "include",
    "3763": "click",
    "3359": "aged",
    "448": "lass",
    "3416": "ison",
    "1521": "\u0120these",
    "1674": "\u0120java",
    "2379": "angu",
    "2255": "andom",
    "1461": "\u0120him",
    "3580": "\u0120See",
    "344": "iv",
    "3831": "\u0120strong",
    "1698": "ware",
    "373": "ame",
    "3081": "output",
    "1850": "*/",
    "1367": "\u0120exp",
    "2000": "for",
    "1696": "\u0109\u0109\u0109\u0109\u0109\u0109",
    "1115": "\u0120This",
    "3837": "_at",
    "571": "\u0120@",
    "3418": "yc",
    "115": "\u00b7",
    "1003": "ash",
    "1960": "itor",
    "2650": "\u0120How",
    "3548": "<String",
    "2077": "\u0120response",
    "1945": "Image",
    "804": "ener",
    "1830": "\u00d1\u0124",
    "4055": "pha",
    "580": "ace",
    "2067": "bl",
    "854": "\u0120null",
    "3107": "product",
    "2636": "500",
    "2085": "\u0120without",
    "645": "les",
    "3752": "\u0120character",
    "3017": "raft",
    "2147": "\u0120AN",
    "1235": "\u0120*\u010a",
    "3006": "Column",
    "749": ".m",
    "410": "00",
    "3356": "*/\u010a",
    "1623": "LO",
    "1476": "ustom",
    "3885": "\u0120others",
    "3448": "aken",
    "1179": "\u0120import",
    "841": "\u0120ne",
    "2496": "irc",
    "3204": "OS",
    "3565": "top",
    "952": "uth",
    "455": "up",
    "3828": "\u0120girl",
    "924": "\u0120su",
    "14": "/",
    "2828": "()->",
    "252": "\u0140",
    "3186": "_info",
    "3848": "VER",
    "865": "\u0120x",
    "514": "\u0120le",
    "1272": "40",
    "2748": "\u0120parent",
    "2134": "\u0120range",
    "2429": "rame",
    "3272": ".model",
    "2859": "atures",
    "4031": "NE",
    "277": "ar",
    "2352": "aster",
    "2402": "ards",
    "338": "\u0120\u0120\u0120\u0120\u0120\u0120\u0120\u0120\u0120\u0120\u0120\u0120\u0120\u0120\u0120\u0120",
    "2026": "rg",
    "2498": "unity",
    "2989": "PL",
    "1610": "reg",
    "1655": "lease",
    "1846": "AD",
    "3472": "KE",
    "1056": "iss",
    "2454": "ched",
    "2311": "ords",
    "2184": "chool",
    "418": "pt",
    "192": "\u0104",
    "3653": "ilar",
    "2029": ".\u00e2\u0122\u013f",
    "1277": "http",
    "1938": "\u0120day",
    "3105": "ama",
    "187": "\u00ff",
    "397": ">\u010a",
    "3042": "amb",
    "687": "\u0120cont",
    "3965": "150",
    "1067": "round",
    "847": "ark",
    "1374": "print",
    "1901": "\u0120Z",
    "2236": "\u0109\u0109\u0109\u0109\u0109\u0109\u0109\u0109",
    "321": "il",
    "597": "\u0120k",
    "3920": "\u0120esc",
    "1525": "ason",
    "2677": "Click",
    "1011": "ength",
    "300": "as",
    "202": "\u010e",
    "3632": "src",
    "672": "ork",
    "1076": "duct",
    "914": "25",
    "577": "\u0120u",
    "958": "\u0120inter",
    "2858": ".text",
    "2153": "\\\"",
    "2917": "\u0120cur",
    "3636": "\u0120password",
    "689": "ia",
    "1425": "ride",
    "4059": "\u0120mind",
    "2139": "\u0120nil",
    "1159": "_T",
    "3838": "\u0120house",
    "2466": "\u0120big",
    "20": "5",
    "3200": "unk",
    "2669": "\u0120>=",
    "2037": "message",
    "3682": "\u0120major",
    "2785": "ling",
    "1151": "='",
    "1282": "],\u010a",
    "712": "\u0120bo",
    "1237": ");",
    "1021": "(\u010a",
    "3445": "\u0120means",
    "3932": "\u0120users",
    "2607": "HT",
    "3891": "GET",
    "3392": "\u0120amount",
    "3152": "\u0120mean",
    "1823": ".B",
    "744": "\u0120System",
    "454": "op",
    "4071": "But",
    "43": "L",
    "1224": "item",
    "3102": "ouch",
    "1419": "23",
    "3677": ").\u010a\u010a",
    "3678": "\u0120mar",
    "311": "\u0120to",
    "2337": ".de",
    "3495": "\u0120research",
    "2427": "-g",
    "1244": "reat",
    "721": "\u0120_",
    "3670": "container",
    "2582": "\u0120Or",
    "1570": "ily",
    "3780": "\u0120buy",
    "833": "eng",
    "1096": "load",
    "2882": "\u0120override",
    "1965": "icon",
    "2902": "-h",
    "3744": "\u0120Part",
    "270": "\u0120th",
    "685": "ance",
    "3396": "\u0120\u00ec",
    "1942": "\u0109s",
    "770": "ree",
    "844": ".T",
    "1968": "ivity",
    "3675": "ien",
    "243": "\u0137",
    "3061": "\u0120Fl",
    "1809": "}\u010d\u010a",
    "2450": "\u0120success",
    "3087": "HER",
    "2432": ")(",
    "2369": "isplay",
    "3615": "ignment",
    "1233": "ics",
    "377": "ck",
    "3598": "Menu",
    "3957": "Is",
    "3798": ".assert",
    "557": "\u0120}\u010a\u010a",
    "1245": "ious",
    "601": "********",
    "1748": "ident",
    "2595": "]\u010a\u010a",
    "3530": "[:",
    "1002": "pect",
    "3508": "\u0120whether",
    "3979": "\u0120Def",
    "285": "is",
    "630": "form",
    "863": "\u00e2\u0122\u013f",
    "1380": "\u0120trans",
    "1608": "\u0120ed",
    "2651": "\u0120*)",
    "462": "ri",
    "3818": "}\u010a\u010a\u010a",
    "1670": "\u0120default",
    "3222": "URL",
    "1491": "\u0120mod",
    "2076": "ags",
    "3308": "\u0120Class",
    "1040": "const",
    "4040": "\u0120particular",
    "2329": "md",
    "3552": "\u0120host",
    "1217": "\u0120user",
    "1085": "#include",
    "3522": "gether",
    "1684": "\u0120view",
    "3713": "apping",
    "3266": "=$",
    "2323": "Test",
    "809": "fer",
    "1783": ".r",
    "1463": "ify",
    "3049": "uture",
    "1290": "elp",
    "1362": "ession",
    "763": "\u0120In",
    "1864": "rem",
    "3379": "'),\u010a",
    "3299": "\u00bb\u00bf",
    "755": "def",
    "3426": "amework",
    "1734": "\\n",
    "2772": "ocial",
    "3170": "author",
    "199": "\u010b",
    "1396": "\u0120number",
    "2610": "\u0120ask",
    "3051": "ernal",
    "1273": "ww",
    "1547": "================",
    "2397": "65",
    "3467": "\u0120DE",
    "2624": "\u0120disc",
    "746": "()\u010a",
    "1111": "AN",
    "2883": "\u0120company",
    "2092": "\u0120sol",
    "2707": "bool",
    "1477": "lient",
    "2900": "func",
    "1750": "IL",
    "703": "($",
    "13": ".",
    "535": "ive",
    "830": "ef",
    "206": "\u0112",
    "4058": "asure",
    "651": "erv",
    "488": "ity",
    "983": "ng",
    "1445": "back",
    "431": "****",
    "97": "\u00a4",
    "1508": "span",
    "1023": "\u0120other",
    "681": "['",
    "1320": "td",
    "1442": "\u0120If",
    "1708": "\u0120Al",
    "824": "\u0120per",
    "911": "gr",
    "2750": "\u0109\u0109\u0109\u0109\u0109\u0109\u0109",
    "4041": "styles",
    "2298": "ron",
    "3228": "ead",
    "214": "\u011a",
    "1775": "olean",
    "3139": "\u0120grow",
    "479": "ment",
    "197": "\u0109",
    "3259": "_count",
    "1161": "(s",
    "1957": "\u0120action",
    "1361": "(c",
    "2741": "prop",
    "1480": "Error",
    "2350": "ething",
    "3860": ".Point",
    "542": "alue",
    "2990": "\u0120\"\\",
    "1863": "ENT",
    "1089": "\u0120ass",
    "892": "\u0120time",
    "3720": "Mode",
    "1297": "\u0120bet",
    "2267": "\u0120fa",
    "3771": "\u0120Christ",
    "2179": "____",
    "2244": "Or",
    "1144": "\u0120\\",
    "201": "\u010d",
    "1206": "\u0120cl",
    "2036": ".x",
    "3024": "\u0120json",
    "2922": "-l",
    "3283": "(h",
    "1634": "ces",
    "1587": "\u0120does",
    "732": ".C",
    "1313": "22",
    "3130": "\u0120room",
    "3819": "vider",
    "2423": "ese",
    "3853": ".swing",
    "1813": "org",
    "103": "\u00aa",
    "3241": "\u0120software",
    "414": "our",
    "3263": "\u0120Reg",
    "2433": "ittle",
    "3197": "\u0120plan",
    "3491": "gle",
    "3089": "\"\"",
    "374": "\u0120is",
    "2531": "\u0120leg",
    "2699": "YPE",
    "1632": ".app",
    "2354": "lation",
    "995": ".set",
    "1602": "\u0109\u010a",
    "1911": "press",
    "466": "ter",
    "2909": "\u0120obj",
    "3461": "Select",
    "2283": ".Get",
    "1216": "ey",
    "2473": "era",
    "2156": "\u00d0\u00bd",
    "2486": "\u0120dem",
    "1251": "ning",
    "1296": "\u0120test",
    "1799": "char",
    "2970": "58",
    "2476": ",\u00e2\u0122\u013f",
    "16": "1",
    "3544": "\u0120large",
    "766": "_f",
    "3": "$",
    "2740": "ically",
    "3820": "\u0120pick",
    "3411": "\u0120looking",
    "2962": "_add",
    "2665": "\u0120cho",
    "3972": "ume",
    "1637": "ward",
    "656": "\u0120do",
    "561": "ast",
    "1252": "\u0120Un",
    "3937": "\u0120mot",
    "1288": "\u0120should",
    "157": "\u00e1",
    "1253": "\u0120may",
    "109": "\u00b1",
    "81": "r",
    "2469": "ots",
    "2691": "<div",
    "3864": "aid",
    "1956": "Date",
    "3474": "\u0120det",
    "3829": "reet",
    "1676": "\u0120Ar",
    "2952": "_DE",
    "348": "\u0120v",
    "3718": "\u0120};\u010a\u010a",
    "3528": "show",
    "1897": "fe",
    "3741": "\u0120impro",
    "210": "\u0116",
    "244": "\u0138",
    "2494": "\u0120node",
    "3251": "ij",
    "154": "\u00de",
    "3664": "CTION",
    "2717": "\u0120<=",
    "506": "\u0120ex",
    "3827": "\u0120tax",
    "4064": "AND",
    "957": "ault",
    "1764": "ma",
    "350": "\u0120T"
}